{
    "SPX_Straddle_Volatility_Capture": {
        "date": "2023-10-27",
        "index_levels": 112.4813907504607,
        "result": {
            "sv_2023-08-21_2023-11-17": {
                "call": {
                    "start_date": "2023-08-21",
                    "strike": 4350,
                    "maturity": "2023-11-17",
                    "units": -0.0010535415908332368,
                    "gamma": 0.0012851451002261287,
                    "vega": 844.9501050243479,
                    "tau": 0.2410958904109589,
                    "delta_t_1": 0.2919223750676584,
                    "option_price_t_1": 10.52,
                    "underlying_t_1": 4137.23,
                    "Option_PnL": 0.0035820414088330046,
                    "Delta_PnL": 0.006107989937691848,
                    "Total_PnL": -0.0025259485288588435,
                    "delta_t": 0.2689706026004695,
                    "option_price_t": 7.12,
                    "underlying_price_t": 4117.37
                },
                "put": {
                    "start_date": "2023-08-21",
                    "strike": 4350,
                    "maturity": "2023-11-17",
                    "units": -0.0010535415908332368,
                    "gamma": 0.0012851451002261287,
                    "vega": 844.9501050243479,
                    "tau": 0.2410958904109589,
                    "delta_t_1": -0.7080776249323416,
                    "option_price_t_1": 223.29,
                    "underlying_t_1": 4137.23,
                    "Option_PnL": -0.017341294585115085,
                    "Delta_PnL": -0.014815346056255889,
                    "Total_PnL": -0.002525948528859196,
                    "delta_t": -0.7310293973995305,
                    "option_price_t": 239.75,
                    "underlying_price_t": 4117.37
                }
            },
            "sv_2023-08-22_2023-11-17": {
                "call": {
                    "start_date": "2023-08-22",
                    "strike": 4400,
                    "maturity": "2023-11-17",
                    "units": -0.0010430781502914273,
                    "gamma": 0.001339287557450647,
                    "vega": 854.5395152993697,
                    "tau": 0.23835616438356164,
                    "delta_t_1": 0.24613944425050954,
                    "option_price_t_1": 5.95,
                    "underlying_t_1": 4137.23,
                    "Option_PnL": 0.0022530488046294834,
                    "Delta_PnL": 0.005098909549780382,
                    "Total_PnL": -0.002845860745150899,
                    "delta_t": 0.22437953980115777,
                    "option_price_t": 3.79,
                    "underlying_price_t": 4117.37
                },
                "put": {
                    "start_date": "2023-08-22",
                    "strike": 4400,
                    "maturity": "2023-11-17",
                    "units": -0.0010430781502914273,
                    "gamma": 0.001339287557450647,
                    "vega": 854.5395152993697,
                    "tau": 0.23835616438356164,
                    "delta_t_1": -0.7538605557494904,
                    "option_price_t_1": 268.72,
                    "underlying_t_1": 4137.23,
                    "Option_PnL": -0.01846248326015825,
                    "Delta_PnL": -0.015616622515007023,
                    "Total_PnL": -0.0028458607451512276,
                    "delta_t": -0.7756204601988422,
                    "option_price_t": 286.42,
                    "underlying_price_t": 4117.37
                }
            },
            "sv_2023-08-23_2023-11-17": {
                "call": {
                    "start_date": "2023-08-23",
                    "strike": 4400,
                    "maturity": "2023-11-17",
                    "units": -0.0010486583705978185,
                    "gamma": 0.0012894742132547091,
                    "vega": 849.0664871799618,
                    "tau": 0.2356164383561644,
                    "delta_t_1": 0.24473315728424683,
                    "option_price_t_1": 5.95,
                    "underlying_t_1": 4137.23,
                    "Option_PnL": 0.0022651020804912883,
                    "Delta_PnL": 0.00509689967262622,
                    "Total_PnL": -0.0028317975921349314,
                    "delta_t": 0.22292348332946477,
                    "option_price_t": 3.79,
                    "underlying_price_t": 4117.37
                },
                "put": {
                    "start_date": "2023-08-23",
                    "strike": 4400,
                    "maturity": "2023-11-17",
                    "units": -0.0010486583705978185,
                    "gamma": 0.0012894742132547091,
                    "vega": 849.0664871799618,
                    "tau": 0.2356164383561644,
                    "delta_t_1": -0.7552668427157532,
                    "option_price_t_1": 268.72,
                    "underlying_t_1": 4137.23,
                    "Option_PnL": -0.018561253159581376,
                    "Delta_PnL": -0.01572945556744611,
                    "Total_PnL": -0.002831797592135265,
                    "delta_t": -0.7770765166705352,
                    "option_price_t": 286.42,
                    "underlying_price_t": 4117.37
                }
            },
            "sv_2023-08-24_2023-11-17": {
                "call": {
                    "start_date": "2023-08-24",
                    "strike": 4450,
                    "maturity": "2023-11-17",
                    "units": -0.0010742164605212967,
                    "gamma": 0.0012714757882277628,
                    "vega": 825.4044014819505,
                    "tau": 0.2328767123287671,
                    "delta_t_1": 0.20297967027249475,
                    "option_price_t_1": 3.21,
                    "underlying_t_1": 4137.23,
                    "Option_PnL": 0.0013857392340724728,
                    "Delta_PnL": 0.004330355884743806,
                    "Total_PnL": -0.0029446166506713334,
                    "delta_t": 0.18276003907717542,
                    "option_price_t": 1.92,
                    "underlying_price_t": 4117.37
                },
                "put": {
                    "start_date": "2023-08-24",
                    "strike": 4450,
                    "maturity": "2023-11-17",
                    "units": -0.0010742164605212967,
                    "gamma": 0.0012714757882277628,
                    "vega": 825.4044014819505,
                    "tau": 0.2328767123287671,
                    "delta_t_1": -0.7970203297275053,
                    "option_price_t_1": 315.98,
                    "underlying_t_1": 4137.23,
                    "Option_PnL": -0.01994819967188047,
                    "Delta_PnL": -0.017003583021208794,
                    "Total_PnL": -0.002944616650671677,
                    "delta_t": -0.8172399609228246,
                    "option_price_t": 334.55,
                    "underlying_price_t": 4117.37
                }
            },
            "sv_2023-08-25_2023-11-17": {
                "call": {
                    "start_date": "2023-08-25",
                    "strike": 4400,
                    "maturity": "2023-11-17",
                    "units": -0.0010534028015225568,
                    "gamma": 0.0012745393346341998,
                    "vega": 841.9606158986842,
                    "tau": 0.23013698630136986,
                    "delta_t_1": 0.24186194173886044,
                    "option_price_t_1": 5.95,
                    "underlying_t_1": 4137.23,
                    "Option_PnL": 0.002275350051288723,
                    "Delta_PnL": 0.005059892013606621,
                    "Total_PnL": -0.002784541962317898,
                    "delta_t": 0.2199532167887201,
                    "option_price_t": 3.79,
                    "underlying_price_t": 4117.37
                },
                "put": {
                    "start_date": "2023-08-25",
                    "strike": 4400,
                    "maturity": "2023-11-17",
                    "units": -0.0010534028015225568,
                    "gamma": 0.0012745393346341998,
                    "vega": 841.9606158986842,
                    "tau": 0.23013698630136986,
                    "delta_t_1": -0.7581380582611396,
                    "option_price_t_1": 268.72,
                    "underlying_t_1": 4137.23,
                    "Option_PnL": -0.018645229586949242,
                    "Delta_PnL": -0.015860687624631015,
                    "Total_PnL": -0.0027845419623182266,
                    "delta_t": -0.7800467832112798,
                    "option_price_t": 286.42,
                    "underlying_price_t": 4117.37
                }
            },
            "sv_2023-08-28_2023-11-17": {
                "call": {
                    "start_date": "2023-08-28",
                    "strike": 4400,
                    "maturity": "2023-11-17",
                    "units": -0.0010782745461772776,
                    "gamma": 0.0012691704235217747,
                    "vega": 824.7488577029384,
                    "tau": 0.2219178082191781,
                    "delta_t_1": 0.23740143863846086,
                    "option_price_t_1": 5.95,
                    "underlying_t_1": 4137.23,
                    "Option_PnL": 0.0023290730197429196,
                    "Delta_PnL": 0.0050838408202029395,
                    "Total_PnL": -0.00275476780046002,
                    "delta_t": 0.21534582177795025,
                    "option_price_t": 3.79,
                    "underlying_price_t": 4117.37
                },
                "put": {
                    "start_date": "2023-08-28",
                    "strike": 4400,
                    "maturity": "2023-11-17",
                    "units": -0.0010782745461772776,
                    "gamma": 0.0012691704235217747,
                    "vega": 824.7488577029384,
                    "tau": 0.2219178082191781,
                    "delta_t_1": -0.7625985613615391,
                    "option_price_t_1": 268.72,
                    "underlying_t_1": 4137.23,
                    "Option_PnL": -0.019085459467337803,
                    "Delta_PnL": -0.01633069166687744,
                    "Total_PnL": -0.002754767800460363,
                    "delta_t": -0.7846541782220497,
                    "option_price_t": 286.42,
                    "underlying_price_t": 4117.37
                }
            },
            "sv_2023-08-29_2023-11-17": {
                "call": {
                    "start_date": "2023-08-29",
                    "strike": 4450,
                    "maturity": "2023-11-17",
                    "units": -0.0010709134389942298,
                    "gamma": 0.0011991410280599432,
                    "vega": 826.1180507595227,
                    "tau": 0.2191780821917808,
                    "delta_t_1": 0.1951336373711819,
                    "option_price_t_1": 3.21,
                    "underlying_t_1": 4137.23,
                    "Option_PnL": 0.0013814783363025566,
                    "Delta_PnL": 0.0041501687203599515,
                    "Total_PnL": -0.002768690384057395,
                    "delta_t": 0.17483331899204285,
                    "option_price_t": 1.92,
                    "underlying_price_t": 4117.37
                },
                "put": {
                    "start_date": "2023-08-29",
                    "strike": 4450,
                    "maturity": "2023-11-17",
                    "units": -0.0010709134389942298,
                    "gamma": 0.0011991410280599432,
                    "vega": 826.1180507595227,
                    "tau": 0.2191780821917808,
                    "delta_t_1": -0.8048663626288182,
                    "option_price_t_1": 315.98,
                    "underlying_t_1": 4137.23,
                    "Option_PnL": -0.01988686256212284,
                    "Delta_PnL": -0.017118172178065102,
                    "Total_PnL": -0.0027686903840577377,
                    "delta_t": -0.8251666810079572,
                    "option_price_t": 334.55,
                    "underlying_price_t": 4117.37
                }
            },
            "sv_2023-08-30_2023-11-17": {
                "call": {
                    "start_date": "2023-08-30",
                    "strike": 4500,
                    "maturity": "2023-11-17",
                    "units": -0.0010596678347740188,
                    "gamma": 0.0012152404496131469,
                    "vega": 835.1624468929853,
                    "tau": 0.21643835616438356,
                    "delta_t_1": 0.1577226699162267,
                    "option_price_t_1": 1.65,
                    "underlying_t_1": 4137.23,
                    "Option_PnL": 0.0007735575193850336,
                    "Delta_PnL": 0.003319274092880563,
                    "Total_PnL": -0.0025457165734955297,
                    "delta_t": 0.1394579944312409,
                    "option_price_t": 0.92,
                    "underlying_price_t": 4117.37
                },
                "put": {
                    "start_date": "2023-08-30",
                    "strike": 4500,
                    "maturity": "2023-11-17",
                    "units": -0.0010596678347740188,
                    "gamma": 0.0012152404496131469,
                    "vega": 835.1624468929853,
                    "tau": 0.21643835616438356,
                    "delta_t_1": -0.8422773300837734,
                    "option_price_t_1": 364.42,
                    "underlying_t_1": 4137.23,
                    "Option_PnL": -0.020271445679226976,
                    "Delta_PnL": -0.017725729105731107,
                    "Total_PnL": -0.002545716573495869,
                    "delta_t": -0.8605420055687591,
                    "option_price_t": 383.55,
                    "underlying_price_t": 4117.37
                }
            },
            "sv_2023-08-31_2023-11-17": {
                "call": {
                    "start_date": "2023-08-31",
                    "strike": 4500,
                    "maturity": "2023-11-17",
                    "units": -0.001068858120978571,
                    "gamma": 0.0012390404178728687,
                    "vega": 829.8378161563892,
                    "tau": 0.2136986301369863,
                    "delta_t_1": 0.1560587527747046,
                    "option_price_t_1": 1.65,
                    "underlying_t_1": 4137.23,
                    "Option_PnL": 0.0007802664283143566,
                    "Delta_PnL": 0.003312740651925123,
                    "Total_PnL": -0.0025324742236107665,
                    "delta_t": 0.1378167858752567,
                    "option_price_t": 0.92,
                    "underlying_price_t": 4117.37
                },
                "put": {
                    "start_date": "2023-08-31",
                    "strike": 4500,
                    "maturity": "2023-11-17",
                    "units": -0.001068858120978571,
                    "gamma": 0.0012390404178728687,
                    "vega": 829.8378161563892,
                    "tau": 0.2136986301369863,
                    "delta_t_1": -0.8439412472252954,
                    "option_price_t_1": 364.42,
                    "underlying_t_1": 4137.23,
                    "Option_PnL": -0.020447255854320057,
                    "Delta_PnL": -0.017914781630708945,
                    "Total_PnL": -0.002532474223611112,
                    "delta_t": -0.8621832141247433,
                    "option_price_t": 383.55,
                    "underlying_price_t": 4117.37
                }
            },
            "sv_2023-09-01_2023-11-17": {
                "call": {
                    "start_date": "2023-09-01",
                    "strike": 4500,
                    "maturity": "2023-11-17",
                    "units": -0.001076653366193522,
                    "gamma": 0.0012414366452256193,
                    "vega": 824.4791174996545,
                    "tau": 0.21095890410958903,
                    "delta_t_1": 0.15437526508776916,
                    "option_price_t_1": 1.65,
                    "underlying_t_1": 4137.23,
                    "Option_PnL": 0.000785956957321271,
                    "Delta_PnL": 0.003300903765441298,
                    "Total_PnL": -0.002514946808120027,
                    "delta_t": 0.13615803680875327,
                    "option_price_t": 0.92,
                    "underlying_price_t": 4117.37
                },
                "put": {
                    "start_date": "2023-09-01",
                    "strike": 4500,
                    "maturity": "2023-11-17",
                    "units": -0.001076653366193522,
                    "gamma": 0.0012414366452256193,
                    "vega": 824.4791174996545,
                    "tau": 0.21095890410958903,
                    "delta_t_1": -0.8456247349122308,
                    "option_price_t_1": 364.42,
                    "underlying_t_1": 4137.23,
                    "Option_PnL": -0.020596378895282073,
                    "Delta_PnL": -0.018081432087161696,
                    "Total_PnL": -0.0025149468081203767,
                    "delta_t": -0.8638419631912467,
                    "option_price_t": 383.55,
                    "underlying_price_t": 4117.37
                }
            },
            "sv_2023-09-05_2023-11-17": {
                "call": {
                    "start_date": "2023-09-05",
                    "strike": 4500,
                    "maturity": "2023-11-17",
                    "units": -0.001113284586400944,
                    "gamma": 0.0012856397513507302,
                    "vega": 802.0538857852889,
                    "tau": 0.2,
                    "delta_t_1": 0.14743873047498812,
                    "option_price_t_1": 1.65,
                    "underlying_t_1": 4137.23,
                    "Option_PnL": 0.000812697748072689,
                    "Delta_PnL": 0.003259845544275809,
                    "Total_PnL": -0.0024471477962031197,
                    "delta_t": 0.1293426799737607,
                    "option_price_t": 0.92,
                    "underlying_price_t": 4117.37
                },
                "put": {
                    "start_date": "2023-09-05",
                    "strike": 4500,
                    "maturity": "2023-11-17",
                    "units": -0.001113284586400944,
                    "gamma": 0.0012856397513507302,
                    "vega": 802.0538857852889,
                    "tau": 0.2,
                    "delta_t_1": -0.8525612695250119,
                    "option_price_t_1": 364.42,
                    "underlying_t_1": 4137.23,
                    "Option_PnL": -0.021297134137850053,
                    "Delta_PnL": -0.018849986341646575,
                    "Total_PnL": -0.0024471477962034784,
                    "delta_t": -0.8706573200262393,
                    "option_price_t": 383.55,
                    "underlying_price_t": 4117.37
                }
            },
            "sv_2023-09-06_2023-11-17": {
                "call": {
                    "start_date": "2023-09-06",
                    "strike": 4500,
                    "maturity": "2023-11-17",
                    "units": -0.0011331691244771658,
                    "gamma": 0.0012908032616753124,
                    "vega": 788.873842756773,
                    "tau": 0.19726027397260273,
                    "delta_t_1": 0.14565218699173454,
                    "option_price_t_1": 1.65,
                    "underlying_t_1": 4137.23,
                    "Option_PnL": 0.000827213460868331,
                    "Delta_PnL": 0.0032778644256624863,
                    "Total_PnL": -0.0024506509647941556,
                    "delta_t": 0.12759251038538338,
                    "option_price_t": 0.92,
                    "underlying_price_t": 4117.37
                },
                "put": {
                    "start_date": "2023-09-06",
                    "strike": 4500,
                    "maturity": "2023-11-17",
                    "units": -0.0011331691244771658,
                    "gamma": 0.0012908032616753124,
                    "vega": 788.873842756773,
                    "tau": 0.19726027397260273,
                    "delta_t_1": -0.8543478130082655,
                    "option_price_t_1": 364.42,
                    "underlying_t_1": 4137.23,
                    "Option_PnL": -0.021677525351248176,
                    "Delta_PnL": -0.019226874386453655,
                    "Total_PnL": -0.0024506509647945207,
                    "delta_t": -0.8724074896146166,
                    "option_price_t": 383.55,
                    "underlying_price_t": 4117.37
                }
            },
            "sv_2023-09-07_2023-11-17": {
                "call": {
                    "start_date": "2023-09-07",
                    "strike": 4450,
                    "maturity": "2023-11-17",
                    "units": -0.0011438863080216746,
                    "gamma": 0.0013052766543625732,
                    "vega": 782.6179915613641,
                    "tau": 0.19452054794520549,
                    "delta_t_1": 0.1796243737041836,
                    "option_price_t_1": 3.21,
                    "underlying_t_1": 4137.23,
                    "Option_PnL": 0.0014756133373479603,
                    "Delta_PnL": 0.00408063145271021,
                    "Total_PnL": -0.00260501811536225,
                    "delta_t": 0.15926071985963403,
                    "option_price_t": 1.92,
                    "underlying_price_t": 4117.37
                },
                "put": {
                    "start_date": "2023-09-07",
                    "strike": 4450,
                    "maturity": "2023-11-17",
                    "units": -0.0011438863080216746,
                    "gamma": 0.0013052766543625732,
                    "vega": 782.6179915613641,
                    "tau": 0.19452054794520549,
                    "delta_t_1": -0.8203756262958164,
                    "option_price_t_1": 315.98,
                    "underlying_t_1": 4137.23,
                    "Option_PnL": -0.02124196873996249,
                    "Delta_PnL": -0.01863695062459987,
                    "Total_PnL": -0.0026050181153626194,
                    "delta_t": -0.8407392801403659,
                    "option_price_t": 334.55,
                    "underlying_price_t": 4117.37
                }
            },
            "sv_2023-09-08_2023-11-17": {
                "call": {
                    "start_date": "2023-09-08",
                    "strike": 4450,
                    "maturity": "2023-11-17",
                    "units": -0.0011539450497489582,
                    "gamma": 0.0013203981122599647,
                    "vega": 777.4190120511192,
                    "tau": 0.1917808219178082,
                    "delta_t_1": 0.1777785336340204,
                    "option_price_t_1": 3.21,
                    "underlying_t_1": 4137.23,
                    "Option_PnL": 0.0014885891141761562,
                    "Delta_PnL": 0.004074212644534658,
                    "Total_PnL": -0.002585623530358502,
                    "delta_t": 0.15741640850033262,
                    "option_price_t": 1.92,
                    "underlying_price_t": 4117.37
                },
                "put": {
                    "start_date": "2023-09-08",
                    "strike": 4450,
                    "maturity": "2023-11-17",
                    "units": -0.0011539450497489582,
                    "gamma": 0.0013203981122599647,
                    "vega": 777.4190120511192,
                    "tau": 0.1917808219178082,
                    "delta_t_1": -0.8222214663659796,
                    "option_price_t_1": 315.98,
                    "underlying_t_1": 4137.23,
                    "Option_PnL": -0.021428759573838146,
                    "Delta_PnL": -0.018843136043479272,
                    "Total_PnL": -0.0025856235303588736,
                    "delta_t": -0.8425835914996673,
                    "option_price_t": 334.55,
                    "underlying_price_t": 4117.37
                }
            },
            "sv_2023-09-11_2023-11-17": {
                "call": {
                    "start_date": "2023-09-11",
                    "strike": 4450,
                    "maturity": "2023-11-17",
                    "units": -0.001190211985486916,
                    "gamma": 0.0013442039838820962,
                    "vega": 757.1288667400096,
                    "tau": 0.18356164383561643,
                    "delta_t_1": 0.17207916987241256,
                    "option_price_t_1": 3.21,
                    "underlying_t_1": 4137.23,
                    "Option_PnL": 0.0015353734612781219,
                    "Delta_PnL": 0.004067540312034753,
                    "Total_PnL": -0.0025321668507566307,
                    "delta_t": 0.1517346730897805,
                    "option_price_t": 1.92,
                    "underlying_price_t": 4117.37
                },
                "put": {
                    "start_date": "2023-09-11",
                    "strike": 4450,
                    "maturity": "2023-11-17",
                    "units": -0.001190211985486916,
                    "gamma": 0.0013442039838820962,
                    "vega": 757.1288667400096,
                    "tau": 0.18356164383561643,
                    "delta_t_1": -0.8279208301275874,
                    "option_price_t_1": 315.98,
                    "underlying_t_1": 4137.23,
                    "Option_PnL": -0.022102236570492022,
                    "Delta_PnL": -0.01957006971973501,
                    "Total_PnL": -0.0025321668507570123,
                    "delta_t": -0.8482653269102195,
                    "option_price_t": 334.55,
                    "underlying_price_t": 4117.37
                }
            },
            "sv_2023-09-12_2023-11-17": {
                "call": {
                    "start_date": "2023-09-12",
                    "strike": 4500,
                    "maturity": "2023-11-17",
                    "units": -0.0011986850111147254,
                    "gamma": 0.0013667859838234436,
                    "vega": 753.2995932174648,
                    "tau": 0.18082191780821918,
                    "delta_t_1": 0.13446449888519774,
                    "option_price_t_1": 1.65,
                    "underlying_t_1": 4137.23,
                    "Option_PnL": 0.0008750400581137494,
                    "Delta_PnL": 0.003201046305707028,
                    "Total_PnL": -0.0023260062475932786,
                    "delta_t": 0.116683504411485,
                    "option_price_t": 0.92,
                    "underlying_price_t": 4117.37
                },
                "put": {
                    "start_date": "2023-09-12",
                    "strike": 4500,
                    "maturity": "2023-11-17",
                    "units": -0.0011986850111147254,
                    "gamma": 0.0013667859838234436,
                    "vega": 753.2995932174648,
                    "tau": 0.18082191780821918,
                    "delta_t_1": -0.8655355011148023,
                    "option_price_t_1": 364.42,
                    "underlying_t_1": 4137.23,
                    "Option_PnL": -0.02293084426262469,
                    "Delta_PnL": -0.020604838015031025,
                    "Total_PnL": -0.0023260062475936663,
                    "delta_t": -0.883316495588515,
                    "option_price_t": 383.55,
                    "underlying_price_t": 4117.37
                }
            },
            "sv_2023-09-13_2023-11-17": {
                "call": {
                    "start_date": "2023-09-13",
                    "strike": 4450,
                    "maturity": "2023-11-17",
                    "units": -0.0012078031109843737,
                    "gamma": 0.0013758131807064967,
                    "vega": 748.8719002445259,
                    "tau": 0.1780821917808219,
                    "delta_t_1": 0.1681384657211379,
                    "option_price_t_1": 3.21,
                    "underlying_t_1": 4137.23,
                    "Option_PnL": 0.0015580660131698423,
                    "Delta_PnL": 0.004033132296806152,
                    "Total_PnL": -0.0024750662836363095,
                    "delta_t": 0.14781790552486757,
                    "option_price_t": 1.92,
                    "underlying_price_t": 4117.37
                },
                "put": {
                    "start_date": "2023-09-13",
                    "strike": 4450,
                    "maturity": "2023-11-17",
                    "units": -0.0012078031109843737,
                    "gamma": 0.0013758131807064967,
                    "vega": 748.8719002445259,
                    "tau": 0.1780821917808219,
                    "delta_t_1": -0.8318615342788621,
                    "option_price_t_1": 315.98,
                    "underlying_t_1": 4137.23,
                    "Option_PnL": -0.02242890377097981,
                    "Delta_PnL": -0.019953837487343116,
                    "Total_PnL": -0.0024750662836366955,
                    "delta_t": -0.8521820944751324,
                    "option_price_t": 334.55,
                    "underlying_price_t": 4117.37
                }
            },
            "sv_2023-09-14_2023-11-17": {
                "call": {
                    "start_date": "2023-09-14",
                    "strike": 4450,
                    "maturity": "2023-11-17",
                    "units": -0.0012336310942686088,
                    "gamma": 0.0013821702986860035,
                    "vega": 733.2198977772277,
                    "tau": 0.17534246575342466,
                    "delta_t_1": 0.16612380967327772,
                    "option_price_t_1": 3.21,
                    "underlying_t_1": 4137.23,
                    "Option_PnL": 0.0015913841116065054,
                    "Delta_PnL": 0.0040700189726306625,
                    "Total_PnL": -0.002478634861024157,
                    "delta_t": 0.14581931129771297,
                    "option_price_t": 1.92,
                    "underlying_price_t": 4117.37
                },
                "put": {
                    "start_date": "2023-09-14",
                    "strike": 4450,
                    "maturity": "2023-11-17",
                    "units": -0.0012336310942686088,
                    "gamma": 0.0013821702986860035,
                    "vega": 733.2198977772277,
                    "tau": 0.17534246575342466,
                    "delta_t_1": -0.8338761903267222,
                    "option_price_t_1": 315.98,
                    "underlying_t_1": 4137.23,
                    "Option_PnL": -0.022908529420568056,
                    "Delta_PnL": -0.020429894559543502,
                    "Total_PnL": -0.002478634861024554,
                    "delta_t": -0.854180688702287,
                    "option_price_t": 334.55,
                    "underlying_price_t": 4117.37
                }
            },
            "sv_2023-09-15_2023-11-17": {
                "call": {
                    "start_date": "2023-09-15",
                    "strike": 4500,
                    "maturity": "2023-11-17",
                    "units": -0.0012313444553016717,
                    "gamma": 0.0013831157325800028,
                    "vega": 730.3209367061918,
                    "tau": 0.1726027397260274,
                    "delta_t_1": 0.12855254048968773,
                    "option_price_t_1": 1.65,
                    "underlying_t_1": 4137.23,
                    "Option_PnL": 0.0008988814523702202,
                    "Delta_PnL": 0.003143688214825792,
                    "Total_PnL": -0.002244806762455572,
                    "delta_t": 0.1109562699628337,
                    "option_price_t": 0.92,
                    "underlying_price_t": 4117.37
                },
                "put": {
                    "start_date": "2023-09-15",
                    "strike": 4500,
                    "maturity": "2023-11-17",
                    "units": -0.0012313444553016717,
                    "gamma": 0.0013831157325800028,
                    "vega": 730.3209367061918,
                    "tau": 0.1726027397260274,
                    "delta_t_1": -0.8714474595103123,
                    "option_price_t_1": 364.42,
                    "underlying_t_1": 4137.23,
                    "Option_PnL": -0.023555619429920974,
                    "Delta_PnL": -0.021310812667465005,
                    "Total_PnL": -0.0022448067624559684,
                    "delta_t": -0.8890437300371663,
                    "option_price_t": 383.55,
                    "underlying_price_t": 4117.37
                }
            },
            "sv_2023-09-18_2023-12-15": {
                "call": {
                    "start_date": "2023-09-18",
                    "strike": 4450,
                    "maturity": "2023-12-15",
                    "units": -0.0010349958745016691,
                    "gamma": 0.0011868410700673188,
                    "vega": 871.3740129436579,
                    "tau": 0.2410958904109589,
                    "delta_t_1": 0.20745343764725205,
                    "option_price_t_1": 17.48,
                    "underlying_t_1": 4137.23,
                    "Option_PnL": 0.00400543403432146,
                    "Delta_PnL": 0.004264209159025579,
                    "Total_PnL": -0.0002587751247041187,
                    "delta_t": 0.187293438437183,
                    "option_price_t": 13.61,
                    "underlying_price_t": 4117.37
                },
                "put": {
                    "start_date": "2023-09-18",
                    "strike": 4450,
                    "maturity": "2023-12-15",
                    "units": -0.0010349958745016691,
                    "gamma": 0.0011868410700673188,
                    "vega": 871.3740129436579,
                    "tau": 0.2410958904109589,
                    "delta_t_1": -0.7925465623527479,
                    "option_price_t_1": 330.25,
                    "underlying_t_1": 4137.23,
                    "Option_PnL": -0.0165495840332817,
                    "Delta_PnL": -0.01629080890857723,
                    "Total_PnL": -0.00025877512470446826,
                    "delta_t": -0.8127065615628171,
                    "option_price_t": 346.24,
                    "underlying_price_t": 4117.37
                }
            },
            "sv_2023-09-19_2023-12-15": {
                "call": {
                    "start_date": "2023-09-19",
                    "strike": 4450,
                    "maturity": "2023-12-15",
                    "units": -0.00104433931946548,
                    "gamma": 0.0012234847937982,
                    "vega": 865.4081857322826,
                    "tau": 0.23835616438356164,
                    "delta_t_1": 0.2059807411794891,
                    "option_price_t_1": 17.48,
                    "underlying_t_1": 4137.23,
                    "Option_PnL": 0.004041593166331408,
                    "Delta_PnL": 0.004272159811138292,
                    "Total_PnL": -0.00023056664480688386,
                    "delta_t": 0.1858000494125958,
                    "option_price_t": 13.61,
                    "underlying_price_t": 4117.37
                },
                "put": {
                    "start_date": "2023-09-19",
                    "strike": 4450,
                    "maturity": "2023-12-15",
                    "units": -0.00104433931946548,
                    "gamma": 0.0012234847937982,
                    "vega": 865.4081857322826,
                    "tau": 0.23835616438356164,
                    "delta_t_1": -0.7940192588205108,
                    "option_price_t_1": 330.25,
                    "underlying_t_1": 4137.23,
                    "Option_PnL": -0.016698985718253033,
                    "Delta_PnL": -0.016468419073445796,
                    "Total_PnL": -0.00023056664480723688,
                    "delta_t": -0.8141999505874042,
                    "option_price_t": 346.24,
                    "underlying_price_t": 4117.37
                }
            },
            "sv_2023-09-20_2023-12-15": {
                "call": {
                    "start_date": "2023-09-20",
                    "strike": 4450,
                    "maturity": "2023-12-15",
                    "units": -0.0010640585941414842,
                    "gamma": 0.0012148238924999113,
                    "vega": 847.469520884936,
                    "tau": 0.2356164383561644,
                    "delta_t_1": 0.20448961268866583,
                    "option_price_t_1": 17.48,
                    "underlying_t_1": 4137.23,
                    "Option_PnL": 0.004117906759327545,
                    "Delta_PnL": 0.004321316145709531,
                    "Total_PnL": -0.00020340938638198618,
                    "delta_t": 0.18428902784209295,
                    "option_price_t": 13.61,
                    "underlying_price_t": 4117.37
                },
                "put": {
                    "start_date": "2023-09-20",
                    "strike": 4450,
                    "maturity": "2023-12-15",
                    "units": -0.0010640585941414842,
                    "gamma": 0.0012148238924999113,
                    "vega": 847.469520884936,
                    "tau": 0.2356164383561644,
                    "delta_t_1": -0.7955103873113342,
                    "option_price_t_1": 330.25,
                    "underlying_t_1": 4137.23,
                    "Option_PnL": -0.01701429692032234,
                    "Delta_PnL": -0.016810887533939996,
                    "Total_PnL": -0.0002034093863823444,
                    "delta_t": -0.815710972157907,
                    "option_price_t": 346.24,
                    "underlying_price_t": 4117.37
                }
            },
            "sv_2023-09-21_2023-12-15": {
                "call": {
                    "start_date": "2023-09-21",
                    "strike": 4400,
                    "maturity": "2023-12-15",
                    "units": -0.001088656446287918,
                    "gamma": 0.0011729374876559152,
                    "vega": 821.8761602548113,
                    "tau": 0.2328767123287671,
                    "delta_t_1": 0.24330747531958524,
                    "option_price_t_1": 24.48,
                    "underlying_t_1": 4137.23,
                    "Option_PnL": 0.005410622538050951,
                    "Delta_PnL": 0.005260482073532874,
                    "Total_PnL": 0.00015014046451807764,
                    "delta_t": 0.22144818489184603,
                    "option_price_t": 19.51,
                    "underlying_price_t": 4117.37
                },
                "put": {
                    "start_date": "2023-09-21",
                    "strike": 4400,
                    "maturity": "2023-12-15",
                    "units": -0.001088656446287918,
                    "gamma": 0.0011729374876559152,
                    "vega": 821.8761602548113,
                    "tau": 0.2328767123287671,
                    "delta_t_1": -0.7566925246804148,
                    "option_price_t_1": 287.25,
                    "underlying_t_1": 4137.23,
                    "Option_PnL": -0.016210094485227085,
                    "Delta_PnL": -0.016360234949744822,
                    "Total_PnL": 0.00015014046451773677,
                    "delta_t": -0.778551815108154,
                    "option_price_t": 302.14,
                    "underlying_price_t": 4117.37
                }
            },
            "sv_2023-09-22_2023-12-15": {
                "call": {
                    "start_date": "2023-09-22",
                    "strike": 4350,
                    "maturity": "2023-12-15",
                    "units": -0.0010839440290540236,
                    "gamma": 0.0011980049760865297,
                    "vega": 825.7018692090577,
                    "tau": 0.23013698630136986,
                    "delta_t_1": 0.28683851060033994,
                    "option_price_t_1": 33.63,
                    "underlying_t_1": 4137.23,
                    "Option_PnL": 0.00674213186071603,
                    "Delta_PnL": 0.006174809452638134,
                    "Total_PnL": 0.0005673224080778956,
                    "delta_t": 0.26357335501073464,
                    "option_price_t": 27.41,
                    "underlying_price_t": 4117.37
                },
                "put": {
                    "start_date": "2023-09-22",
                    "strike": 4350,
                    "maturity": "2023-12-15",
                    "units": -0.0010839440290540236,
                    "gamma": 0.0011980049760865297,
                    "vega": 825.7018692090577,
                    "tau": 0.23013698630136986,
                    "delta_t_1": -0.7131614893996601,
                    "option_price_t_1": 246.4,
                    "underlying_t_1": 4137.23,
                    "Option_PnL": -0.014784996556296897,
                    "Delta_PnL": -0.015352318964374419,
                    "Total_PnL": 0.0005673224080775217,
                    "delta_t": -0.7364266449892654,
                    "option_price_t": 260.04,
                    "underlying_price_t": 4117.37
                }
            },
            "sv_2023-09-25_2023-12-15": {
                "call": {
                    "start_date": "2023-09-25",
                    "strike": 4300,
                    "maturity": "2023-12-15",
                    "units": -0.0011137235085478352,
                    "gamma": 0.0011958615843862908,
                    "vega": 805.7864043634846,
                    "tau": 0.2219178082191781,
                    "delta_t_1": 0.33263459580400434,
                    "option_price_t_1": 45.36,
                    "underlying_t_1": 4137.23,
                    "Option_PnL": 0.008497710370219985,
                    "Delta_PnL": 0.007357394566389962,
                    "Total_PnL": 0.0011403158038300236,
                    "delta_t": 0.30809552203214485,
                    "option_price_t": 37.73,
                    "underlying_price_t": 4117.37
                },
                "put": {
                    "start_date": "2023-09-25",
                    "strike": 4300,
                    "maturity": "2023-12-15",
                    "units": -0.0011137235085478352,
                    "gamma": 0.0011958615843862908,
                    "vega": 805.7864043634846,
                    "tau": 0.2219178082191781,
                    "delta_t_1": -0.6673654041959957,
                    "option_price_t_1": 208.13,
                    "underlying_t_1": 4137.23,
                    "Option_PnL": -0.013620838509540045,
                    "Delta_PnL": -0.014761154313369681,
                    "Total_PnL": 0.001140315803829636,
                    "delta_t": -0.6919044779678551,
                    "option_price_t": 220.36,
                    "underlying_price_t": 4117.37
                }
            },
            "sv_2023-09-26_2023-12-15": {
                "call": {
                    "start_date": "2023-09-26",
                    "strike": 4350,
                    "maturity": "2023-12-15",
                    "units": -0.0011368428735779438,
                    "gamma": 0.0011792391523131032,
                    "vega": 784.0100673697852,
                    "tau": 0.2191780821917808,
                    "delta_t_1": 0.28144163731775695,
                    "option_price_t_1": 33.63,
                    "underlying_t_1": 4137.23,
                    "Option_PnL": 0.007071162673654813,
                    "Delta_PnL": 0.0063543047054961084,
                    "Total_PnL": 0.0007168579681587047,
                    "delta_t": 0.25785391442634087,
                    "option_price_t": 27.41,
                    "underlying_price_t": 4117.37
                },
                "put": {
                    "start_date": "2023-09-26",
                    "strike": 4350,
                    "maturity": "2023-12-15",
                    "units": -0.0011368428735779438,
                    "gamma": 0.0011792391523131032,
                    "vega": 784.0100673697852,
                    "tau": 0.2191780821917808,
                    "delta_t_1": -0.718558362682243,
                    "option_price_t_1": 246.4,
                    "underlying_t_1": 4137.23,
                    "Option_PnL": -0.01550653679560317,
                    "Delta_PnL": -0.016223394763761483,
                    "Total_PnL": 0.0007168579681583135,
                    "delta_t": -0.7421460855736591,
                    "option_price_t": 260.04,
                    "underlying_price_t": 4117.37
                }
            },
            "sv_2023-09-27_2023-12-15": {
                "call": {
                    "start_date": "2023-09-27",
                    "strike": 4250,
                    "maturity": "2023-12-15",
                    "units": -0.0011332537670062982,
                    "gamma": 0.0012259884910959258,
                    "vega": 788.222885327978,
                    "tau": 0.21643835616438356,
                    "delta_t_1": 0.38444825158145235,
                    "option_price_t_1": 60.04,
                    "underlying_t_1": 4137.23,
                    "Option_PnL": 0.010346606892767505,
                    "Delta_PnL": 0.008652553746367862,
                    "Total_PnL": 0.0016940531463996433,
                    "delta_t": 0.3591090255614866,
                    "option_price_t": 50.91,
                    "underlying_price_t": 4117.37
                },
                "put": {
                    "start_date": "2023-09-27",
                    "strike": 4250,
                    "maturity": "2023-12-15",
                    "units": -0.0011332537670062982,
                    "gamma": 0.0012259884910959258,
                    "vega": 788.222885327978,
                    "tau": 0.21643835616438356,
                    "delta_t_1": -0.6155517484185477,
                    "option_price_t_1": 172.81,
                    "underlying_t_1": 4137.23,
                    "Option_PnL": -0.012159812919977567,
                    "Delta_PnL": -0.01385386606637685,
                    "Total_PnL": 0.0016940531463992825,
                    "delta_t": -0.6408909744385134,
                    "option_price_t": 183.54,
                    "underlying_price_t": 4117.37
                }
            },
            "sv_2023-09-28_2023-12-15": {
                "call": {
                    "start_date": "2023-09-28",
                    "strike": 4250,
                    "maturity": "2023-12-15",
                    "units": -0.0011498778459045405,
                    "gamma": 0.0012107665038441067,
                    "vega": 778.450582440317,
                    "tau": 0.2136986301369863,
                    "delta_t_1": 0.38353530407052827,
                    "option_price_t_1": 60.04,
                    "underlying_t_1": 4137.23,
                    "Option_PnL": 0.010498384733108457,
                    "Delta_PnL": 0.00875863236056088,
                    "Total_PnL": 0.0017397523725475768,
                    "delta_t": 0.35805917611057503,
                    "option_price_t": 50.91,
                    "underlying_price_t": 4117.37
                },
                "put": {
                    "start_date": "2023-09-28",
                    "strike": 4250,
                    "maturity": "2023-12-15",
                    "units": -0.0011498778459045405,
                    "gamma": 0.0012107665038441067,
                    "vega": 778.450582440317,
                    "tau": 0.2136986301369863,
                    "delta_t_1": -0.6164646959294717,
                    "option_price_t_1": 172.81,
                    "underlying_t_1": 4137.23,
                    "Option_PnL": -0.012338189286555707,
                    "Delta_PnL": -0.014077941659102916,
                    "Total_PnL": 0.001739752372547209,
                    "delta_t": -0.641940823889425,
                    "option_price_t": 183.54,
                    "underlying_price_t": 4117.37
                }
            },
            "sv_2023-09-29_2023-12-15": {
                "call": {
                    "start_date": "2023-09-29",
                    "strike": 4300,
                    "maturity": "2023-12-15",
                    "units": -0.0011398892886089042,
                    "gamma": 0.0012571717894205906,
                    "vega": 785.7217185888775,
                    "tau": 0.21095890410958903,
                    "delta_t_1": 0.3278674386887561,
                    "option_price_t_1": 45.36,
                    "underlying_t_1": 4137.23,
                    "Option_PnL": 0.008697355272085943,
                    "Delta_PnL": 0.007422329067496579,
                    "Total_PnL": 0.001275026204589364,
                    "delta_t": 0.30287796288074764,
                    "option_price_t": 37.73,
                    "underlying_price_t": 4117.37
                },
                "put": {
                    "start_date": "2023-09-29",
                    "strike": 4300,
                    "maturity": "2023-12-15",
                    "units": -0.0011398892886089042,
                    "gamma": 0.0012571717894205906,
                    "vega": 785.7217185888775,
                    "tau": 0.21095890410958903,
                    "delta_t_1": -0.6721325613112439,
                    "option_price_t_1": 208.13,
                    "underlying_t_1": 4137.23,
                    "Option_PnL": -0.013940845999686919,
                    "Delta_PnL": -0.015215872204275884,
                    "Total_PnL": 0.0012750262045889658,
                    "delta_t": -0.6971220371192524,
                    "option_price_t": 220.36,
                    "underlying_price_t": 4117.37
                }
            },
            "sv_2023-10-02_2023-12-15": {
                "call": {
                    "start_date": "2023-10-02",
                    "strike": 4300,
                    "maturity": "2023-12-15",
                    "units": -0.001165366312119402,
                    "gamma": 0.001282222273728389,
                    "vega": 770.3242253588497,
                    "tau": 0.20273972602739726,
                    "delta_t_1": 0.3240743161165357,
                    "option_price_t_1": 45.36,
                    "underlying_t_1": 4137.23,
                    "Option_PnL": 0.008891744961471042,
                    "Delta_PnL": 0.007500432671819218,
                    "Total_PnL": 0.0013913122896518238,
                    "delta_t": 0.29873138350673223,
                    "option_price_t": 37.73,
                    "underlying_price_t": 4117.37
                },
                "put": {
                    "start_date": "2023-10-02",
                    "strike": 4300,
                    "maturity": "2023-12-15",
                    "units": -0.001165366312119402,
                    "gamma": 0.001282222273728389,
                    "vega": 770.3242253588497,
                    "tau": 0.20273972602739726,
                    "delta_t_1": -0.6759256838834643,
                    "option_price_t_1": 208.13,
                    "underlying_t_1": 4137.23,
                    "Option_PnL": -0.014252429997220309,
                    "Delta_PnL": -0.015643742286871723,
                    "Total_PnL": 0.0013913122896514144,
                    "delta_t": -0.7012686164932678,
                    "option_price_t": 220.36,
                    "underlying_price_t": 4117.37
                }
            },
            "sv_2023-10-03_2023-12-15": {
                "call": {
                    "start_date": "2023-10-03",
                    "strike": 4300,
                    "maturity": "2023-12-15",
                    "units": -0.0012018553411109226,
                    "gamma": 0.0012573725591268872,
                    "vega": 741.426596453412,
                    "tau": 0.2,
                    "delta_t_1": 0.32276506460511933,
                    "option_price_t_1": 45.36,
                    "underlying_t_1": 4137.23,
                    "Option_PnL": 0.009170156252676342,
                    "Delta_PnL": 0.007704029968038613,
                    "Total_PnL": 0.001466126284637729,
                    "delta_t": 0.2973011909511991,
                    "option_price_t": 37.73,
                    "underlying_price_t": 4117.37
                },
                "put": {
                    "start_date": "2023-10-03",
                    "strike": 4300,
                    "maturity": "2023-12-15",
                    "units": -0.0012018553411109226,
                    "gamma": 0.0012573725591268872,
                    "vega": 741.426596453412,
                    "tau": 0.2,
                    "delta_t_1": -0.6772349353948807,
                    "option_price_t_1": 208.13,
                    "underlying_t_1": 4137.23,
                    "Option_PnL": -0.014698690821786606,
                    "Delta_PnL": -0.01616481710642392,
                    "Total_PnL": 0.0014661262846373136,
                    "delta_t": -0.7026988090488009,
                    "option_price_t": 220.36,
                    "underlying_price_t": 4117.37
                }
            },
            "sv_2023-10-04_2023-12-15": {
                "call": {
                    "start_date": "2023-10-04",
                    "strike": 4250,
                    "maturity": "2023-12-15",
                    "units": -0.0011858830683761702,
                    "gamma": 0.0012525453936279955,
                    "vega": 753.0270799727522,
                    "tau": 0.19726027397260273,
                    "delta_t_1": 0.37770797684300694,
                    "option_price_t_1": 60.04,
                    "underlying_t_1": 4137.23,
                    "Option_PnL": 0.010827112414274438,
                    "Delta_PnL": 0.008895641441340639,
                    "Total_PnL": 0.0019314709729337989,
                    "delta_t": 0.35136056653109304,
                    "option_price_t": 50.91,
                    "underlying_price_t": 4117.37
                },
                "put": {
                    "start_date": "2023-10-04",
                    "strike": 4250,
                    "maturity": "2023-12-15",
                    "units": -0.0011858830683761702,
                    "gamma": 0.0012525453936279955,
                    "vega": 753.0270799727522,
                    "tau": 0.19726027397260273,
                    "delta_t_1": -0.6222920231569931,
                    "option_price_t_1": 172.81,
                    "underlying_t_1": 4137.23,
                    "Option_PnL": -0.012724525323676295,
                    "Delta_PnL": -0.014655996296609712,
                    "Total_PnL": 0.0019314709729334172,
                    "delta_t": -0.648639433468907,
                    "option_price_t": 183.54,
                    "underlying_price_t": 4117.37
                }
            },
            "sv_2023-10-05_2023-12-15": {
                "call": {
                    "start_date": "2023-10-05",
                    "strike": 4250,
                    "maturity": "2023-12-15",
                    "units": -0.001196928536373385,
                    "gamma": 0.00130445202918578,
                    "vega": 747.7634228205429,
                    "tau": 0.19452054794520549,
                    "delta_t_1": 0.37667336831132514,
                    "option_price_t_1": 60.04,
                    "underlying_t_1": 4137.23,
                    "Option_PnL": 0.010927957537089009,
                    "Delta_PnL": 0.008953902913994682,
                    "Total_PnL": 0.0019740546230943273,
                    "delta_t": 0.35017180184624036,
                    "option_price_t": 50.91,
                    "underlying_price_t": 4117.37
                },
                "put": {
                    "start_date": "2023-10-05",
                    "strike": 4250,
                    "maturity": "2023-12-15",
                    "units": -0.001196928536373385,
                    "gamma": 0.00130445202918578,
                    "vega": 747.7634228205429,
                    "tau": 0.19452054794520549,
                    "delta_t_1": -0.6233266316886749,
                    "option_price_t_1": 172.81,
                    "underlying_t_1": 4137.23,
                    "Option_PnL": -0.012843043195286409,
                    "Delta_PnL": -0.014817097818380354,
                    "Total_PnL": 0.0019740546230939456,
                    "delta_t": -0.6498281981537597,
                    "option_price_t": 183.54,
                    "underlying_price_t": 4117.37
                }
            },
            "sv_2023-10-06_2023-12-15": {
                "call": {
                    "start_date": "2023-10-06",
                    "strike": 4250,
                    "maturity": "2023-12-15",
                    "units": -0.001225182328787114,
                    "gamma": 0.001267127076512161,
                    "vega": 733.4842920897609,
                    "tau": 0.1917808219178082,
                    "delta_t_1": 0.37561903294187327,
                    "option_price_t_1": 60.04,
                    "underlying_t_1": 4137.23,
                    "Option_PnL": 0.011185914661826354,
                    "Delta_PnL": 0.0091396077781173,
                    "Total_PnL": 0.0020463068837090533,
                    "delta_t": 0.3489605594395442,
                    "option_price_t": 50.91,
                    "underlying_price_t": 4117.37
                },
                "put": {
                    "start_date": "2023-10-06",
                    "strike": 4250,
                    "maturity": "2023-12-15",
                    "units": -0.001225182328787114,
                    "gamma": 0.001267127076512161,
                    "vega": 733.4842920897609,
                    "tau": 0.1917808219178082,
                    "delta_t_1": -0.6243809670581267,
                    "option_price_t_1": 172.81,
                    "underlying_t_1": 4137.23,
                    "Option_PnL": -0.013146206387885722,
                    "Delta_PnL": -0.015192513271594384,
                    "Total_PnL": 0.0020463068837086613,
                    "delta_t": -0.6510394405604558,
                    "option_price_t": 183.54,
                    "underlying_price_t": 4117.37
                }
            },
            "sv_2023-10-09_2023-12-15": {
                "call": {
                    "start_date": "2023-10-09",
                    "strike": 4300,
                    "maturity": "2023-12-15",
                    "units": -0.0012334668581060273,
                    "gamma": 0.001307019908567558,
                    "vega": 732.386605916003,
                    "tau": 0.18356164383561643,
                    "delta_t_1": 0.31438646954567184,
                    "option_price_t_1": 45.36,
                    "underlying_t_1": 4137.23,
                    "Option_PnL": 0.009411352127348992,
                    "Delta_PnL": 0.007701415875715778,
                    "Total_PnL": 0.0017099362516332138,
                    "delta_t": 0.28816229389091674,
                    "option_price_t": 37.73,
                    "underlying_price_t": 4117.37
                },
                "put": {
                    "start_date": "2023-10-09",
                    "strike": 4300,
                    "maturity": "2023-12-15",
                    "units": -0.0012334668581060273,
                    "gamma": 0.001307019908567558,
                    "vega": 732.386605916003,
                    "tau": 0.18356164383561643,
                    "delta_t_1": -0.6856135304543282,
                    "option_price_t_1": 208.13,
                    "underlying_t_1": 4137.23,
                    "Option_PnL": -0.015085299674636737,
                    "Delta_PnL": -0.01679523592626952,
                    "Total_PnL": 0.0017099362516327845,
                    "delta_t": -0.7118377061090833,
                    "option_price_t": 220.36,
                    "underlying_price_t": 4117.37
                }
            },
            "sv_2023-10-10_2023-12-15": {
                "call": {
                    "start_date": "2023-10-10",
                    "strike": 4350,
                    "maturity": "2023-12-15",
                    "units": -0.0012280989778680708,
                    "gamma": 0.0013268764451444587,
                    "vega": 737.9286822920816,
                    "tau": 0.18082191780821918,
                    "delta_t_1": 0.25953422052270125,
                    "option_price_t_1": 33.63,
                    "underlying_t_1": 4137.23,
                    "Option_PnL": 0.0076387756423394034,
                    "Delta_PnL": 0.006330051499381813,
                    "Total_PnL": 0.00130872414295759,
                    "delta_t": 0.23475537277205172,
                    "option_price_t": 27.41,
                    "underlying_price_t": 4117.37
                },
                "put": {
                    "start_date": "2023-10-10",
                    "strike": 4350,
                    "maturity": "2023-12-15",
                    "units": -0.0012280989778680708,
                    "gamma": 0.0013268764451444587,
                    "vega": 737.9286822920816,
                    "tau": 0.18082191780821918,
                    "delta_t_1": -0.7404657794772987,
                    "option_price_t_1": 246.4,
                    "underlying_t_1": 4137.23,
                    "Option_PnL": -0.016751270058120504,
                    "Delta_PnL": -0.01805999420107767,
                    "Total_PnL": 0.0013087241429571676,
                    "delta_t": -0.7652446272279483,
                    "option_price_t": 260.04,
                    "underlying_price_t": 4117.37
                }
            },
            "sv_2023-10-11_2023-12-15": {
                "call": {
                    "start_date": "2023-10-11",
                    "strike": 4350,
                    "maturity": "2023-12-15",
                    "units": -0.0012477394471974558,
                    "gamma": 0.0013873933883126427,
                    "vega": 730.9195289165629,
                    "tau": 0.1780821917808219,
                    "delta_t_1": 0.25775418168399367,
                    "option_price_t_1": 33.63,
                    "underlying_t_1": 4137.23,
                    "Option_PnL": 0.007760939361568178,
                    "Delta_PnL": 0.006387175794920861,
                    "Total_PnL": 0.0013737635666473168,
                    "delta_t": 0.23288762009257863,
                    "option_price_t": 27.41,
                    "underlying_price_t": 4117.37
                },
                "put": {
                    "start_date": "2023-10-11",
                    "strike": 4350,
                    "maturity": "2023-12-15",
                    "units": -0.0012477394471974558,
                    "gamma": 0.0013873933883126427,
                    "vega": 730.9195289165629,
                    "tau": 0.1780821917808219,
                    "delta_t_1": -0.7422458183160063,
                    "option_price_t_1": 246.4,
                    "underlying_t_1": 4137.23,
                    "Option_PnL": -0.017019166059773317,
                    "Delta_PnL": -0.018392929626420203,
                    "Total_PnL": 0.0013737635666468857,
                    "delta_t": -0.7671123799074213,
                    "option_price_t": 260.04,
                    "underlying_price_t": 4117.37
                }
            },
            "sv_2023-10-12_2023-12-15": {
                "call": {
                    "start_date": "2023-10-12",
                    "strike": 4400,
                    "maturity": "2023-12-15",
                    "units": -0.0012658449023771022,
                    "gamma": 0.0014024603640091227,
                    "vega": 718.9479800219344,
                    "tau": 0.17534246575342466,
                    "delta_t_1": 0.20792413287443645,
                    "option_price_t_1": 24.48,
                    "underlying_t_1": 4137.23,
                    "Option_PnL": 0.006291249164814197,
                    "Delta_PnL": 0.005227146115090366,
                    "Total_PnL": 0.0010641030497238304,
                    "delta_t": 0.1851331975802581,
                    "option_price_t": 19.51,
                    "underlying_price_t": 4117.37
                },
                "put": {
                    "start_date": "2023-10-12",
                    "strike": 4400,
                    "maturity": "2023-12-15",
                    "units": -0.0012658449023771022,
                    "gamma": 0.0014024603640091227,
                    "vega": 718.9479800219344,
                    "tau": 0.17534246575342466,
                    "delta_t_1": -0.7920758671255635,
                    "option_price_t_1": 287.25,
                    "underlying_t_1": 4137.23,
                    "Option_PnL": -0.018848430596395033,
                    "Delta_PnL": -0.019912533646118467,
                    "Total_PnL": 0.001064103049723434,
                    "delta_t": -0.8148668024197419,
                    "option_price_t": 302.14,
                    "underlying_price_t": 4117.37
                }
            },
            "sv_2023-10-13_2023-12-15": {
                "call": {
                    "start_date": "2023-10-13",
                    "strike": 4350,
                    "maturity": "2023-12-15",
                    "units": -0.001267717012904408,
                    "gamma": 0.0014293789084588416,
                    "vega": 716.4955580698833,
                    "tau": 0.1726027397260274,
                    "delta_t_1": 0.25409230894150314,
                    "option_price_t_1": 33.63,
                    "underlying_t_1": 4137.23,
                    "Option_PnL": 0.00788519982026542,
                    "Delta_PnL": 0.006397246457860959,
                    "Total_PnL": 0.0014879533624044617,
                    "delta_t": 0.2290499220897098,
                    "option_price_t": 27.41,
                    "underlying_price_t": 4117.37
                },
                "put": {
                    "start_date": "2023-10-13",
                    "strike": 4350,
                    "maturity": "2023-12-15",
                    "units": -0.001267717012904408,
                    "gamma": 0.0014293789084588416,
                    "vega": 716.4955580698833,
                    "tau": 0.1726027397260274,
                    "delta_t_1": -0.7459076910584969,
                    "option_price_t_1": 246.4,
                    "underlying_t_1": 4137.23,
                    "Option_PnL": -0.017291660056016143,
                    "Delta_PnL": -0.018779613418420167,
                    "Total_PnL": 0.0014879533624040236,
                    "delta_t": -0.7709500779102902,
                    "option_price_t": 260.04,
                    "underlying_price_t": 4117.37
                }
            },
            "sv_2023-10-16_2023-12-15": {
                "call": {
                    "start_date": "2023-10-16",
                    "strike": 4350,
                    "maturity": "2023-12-15",
                    "units": -0.0012989545438339355,
                    "gamma": 0.001398175603766593,
                    "vega": 702.6827021615495,
                    "tau": 0.1643835616438356,
                    "delta_t_1": 0.24832794897137095,
                    "option_price_t_1": 33.63,
                    "underlying_t_1": 4137.23,
                    "Option_PnL": 0.008079497262647083,
                    "Delta_PnL": 0.006406175013071548,
                    "Total_PnL": 0.0016733222495755344,
                    "delta_t": 0.223021760822743,
                    "option_price_t": 27.41,
                    "underlying_price_t": 4117.37
                },
                "put": {
                    "start_date": "2023-10-16",
                    "strike": 4350,
                    "maturity": "2023-12-15",
                    "units": -0.0012989545438339355,
                    "gamma": 0.001398175603766593,
                    "vega": 702.6827021615495,
                    "tau": 0.1643835616438356,
                    "delta_t_1": -0.751672051028629,
                    "option_price_t_1": 246.4,
                    "underlying_t_1": 4137.23,
                    "Option_PnL": -0.0177177399778949,
                    "Delta_PnL": -0.019391062227469984,
                    "Total_PnL": 0.0016733222495750842,
                    "delta_t": -0.7769782391772571,
                    "option_price_t": 260.04,
                    "underlying_price_t": 4117.37
                }
            },
            "sv_2023-10-17_2023-12-15": {
                "call": {
                    "start_date": "2023-10-17",
                    "strike": 4350,
                    "maturity": "2023-12-15",
                    "units": -0.001311750002998564,
                    "gamma": 0.0014133132597179952,
                    "vega": 696.8132915554581,
                    "tau": 0.16164383561643836,
                    "delta_t_1": 0.24632915872814287,
                    "option_price_t_1": 33.63,
                    "underlying_t_1": 4137.23,
                    "Option_PnL": 0.008159085018651072,
                    "Delta_PnL": 0.0064172083755473595,
                    "Total_PnL": 0.0017418766431037125,
                    "delta_t": 0.22093531548671824,
                    "option_price_t": 27.41,
                    "underlying_price_t": 4117.37
                },
                "put": {
                    "start_date": "2023-10-17",
                    "strike": 4350,
                    "maturity": "2023-12-15",
                    "units": -0.001311750002998564,
                    "gamma": 0.0014133132597179952,
                    "vega": 696.8132915554581,
                    "tau": 0.16164383561643836,
                    "delta_t_1": -0.7536708412718571,
                    "option_price_t_1": 246.4,
                    "underlying_t_1": 4137.23,
                    "Option_PnL": -0.017892270040900434,
                    "Delta_PnL": -0.019634146684003696,
                    "Total_PnL": 0.0017418766431032615,
                    "delta_t": -0.7790646845132818,
                    "option_price_t": 260.04,
                    "underlying_price_t": 4117.37
                }
            },
            "sv_2023-10-18_2023-12-15": {
                "call": {
                    "start_date": "2023-10-18",
                    "strike": 4350,
                    "maturity": "2023-12-15",
                    "units": -0.0013229210311687264,
                    "gamma": 0.0014104036361138146,
                    "vega": 683.2170925423912,
                    "tau": 0.1589041095890411,
                    "delta_t_1": 0.2442894783600465,
                    "option_price_t_1": 33.63,
                    "underlying_t_1": 4137.23,
                    "Option_PnL": 0.00822856881386948,
                    "Delta_PnL": 0.00641826917590855,
                    "Total_PnL": 0.001810299637960931,
                    "delta_t": 0.21880826556499033,
                    "option_price_t": 27.41,
                    "underlying_price_t": 4117.37
                },
                "put": {
                    "start_date": "2023-10-18",
                    "strike": 4350,
                    "maturity": "2023-12-15",
                    "units": -0.0013229210311687264,
                    "gamma": 0.0014104036361138146,
                    "vega": 683.2170925423912,
                    "tau": 0.1589041095890411,
                    "delta_t_1": -0.7557105216399536,
                    "option_price_t_1": 246.4,
                    "underlying_t_1": 4137.23,
                    "Option_PnL": -0.018044642865141448,
                    "Delta_PnL": -0.019854942503101925,
                    "Total_PnL": 0.0018102996379604774,
                    "delta_t": -0.7811917344350097,
                    "option_price_t": 260.04,
                    "underlying_price_t": 4117.37
                }
            },
            "sv_2023-10-19_2023-12-15": {
                "call": {
                    "start_date": "2023-10-19",
                    "strike": 4300,
                    "maturity": "2023-12-15",
                    "units": -0.0013334706439005882,
                    "gamma": 0.001424637690487041,
                    "vega": 673.7322963772003,
                    "tau": 0.15616438356164383,
                    "delta_t_1": 0.29800456222201543,
                    "option_price_t_1": 45.36,
                    "underlying_t_1": 4137.23,
                    "Option_PnL": 0.010174381012961491,
                    "Delta_PnL": 0.007891973462463935,
                    "Total_PnL": 0.0022824075504975557,
                    "delta_t": 0.2703696569355515,
                    "option_price_t": 37.73,
                    "underlying_price_t": 4117.37
                },
                "put": {
                    "start_date": "2023-10-19",
                    "strike": 4300,
                    "maturity": "2023-12-15",
                    "units": -0.0013334706439005882,
                    "gamma": 0.001424637690487041,
                    "vega": 673.7322963772003,
                    "tau": 0.15616438356164383,
                    "delta_t_1": -0.7019954377779846,
                    "option_price_t_1": 208.13,
                    "underlying_t_1": 4137.23,
                    "Option_PnL": -0.016308345974904218,
                    "Delta_PnL": -0.01859075352540131,
                    "Total_PnL": 0.0022824075504970925,
                    "delta_t": -0.7296303430644485,
                    "option_price_t": 220.36,
                    "underlying_price_t": 4117.37
                }
            },
            "sv_2023-10-20_2023-12-15": {
                "call": {
                    "start_date": "2023-10-20",
                    "strike": 4300,
                    "maturity": "2023-12-15",
                    "units": -0.0013991453351713977,
                    "gamma": 0.0013847735672107438,
                    "vega": 642.0973653532402,
                    "tau": 0.15342465753424658,
                    "delta_t_1": 0.2961638488878941,
                    "option_price_t_1": 45.36,
                    "underlying_t_1": 4137.23,
                    "Option_PnL": 0.010675478907357767,
                    "Delta_PnL": 0.008229512674891432,
                    "Total_PnL": 0.002445966232466335,
                    "delta_t": 0.2683773332488417,
                    "option_price_t": 37.73,
                    "underlying_price_t": 4117.37
                },
                "put": {
                    "start_date": "2023-10-20",
                    "strike": 4300,
                    "maturity": "2023-12-15",
                    "units": -0.0013991453351713977,
                    "gamma": 0.0013847735672107438,
                    "vega": 642.0973653532402,
                    "tau": 0.15342465753424658,
                    "delta_t_1": -0.7038361511121058,
                    "option_price_t_1": 208.13,
                    "underlying_t_1": 4137.23,
                    "Option_PnL": -0.017111547449146218,
                    "Delta_PnL": -0.019557513681612064,
                    "Total_PnL": 0.002445966232465846,
                    "delta_t": -0.7316226667511583,
                    "option_price_t": 220.36,
                    "underlying_price_t": 4117.37
                }
            },
            "sv_2023-10-23_2024-01-19": {
                "call": {
                    "start_date": "2023-10-23",
                    "strike": 4200,
                    "maturity": "2024-01-19",
                    "units": -0.0010952709864238159,
                    "gamma": 0.0011500370916221186,
                    "vega": 822.6947364084548,
                    "tau": 0.2410958904109589,
                    "delta_t_1": 0.4464038252095773,
                    "option_price_t_1": 109.69,
                    "underlying_t_1": 4137.23,
                    "Option_PnL": 0.012705143442516258,
                    "Delta_PnL": 0.009710212517495716,
                    "Total_PnL": 0.0029949309250205426,
                    "delta_t": 0.42230601982681754,
                    "option_price_t": 98.09,
                    "underlying_price_t": 4117.37
                },
                "put": {
                    "start_date": "2023-10-23",
                    "strike": 4200,
                    "maturity": "2024-01-19",
                    "units": -0.0010952709864238159,
                    "gamma": 0.0011500370916221186,
                    "vega": 822.6947364084548,
                    "tau": 0.2410958904109589,
                    "delta_t_1": -0.5535961747904228,
                    "option_price_t_1": 172.46,
                    "underlying_t_1": 4137.23,
                    "Option_PnL": -0.00904693834786071,
                    "Delta_PnL": -0.01204186927288091,
                    "Total_PnL": 0.002994930925020201,
                    "delta_t": -0.5776939801731824,
                    "option_price_t": 180.72,
                    "underlying_price_t": 4117.37
                }
            },
            "sv_2023-10-24_2024-01-19": {
                "call": {
                    "start_date": "2023-10-24",
                    "strike": 4200,
                    "maturity": "2024-01-19",
                    "units": -0.0011078327012479163,
                    "gamma": 0.0011194128663858977,
                    "vega": 814.3220914398405,
                    "tau": 0.23835616438356164,
                    "delta_t_1": 0.44590664079350095,
                    "option_price_t_1": 109.69,
                    "underlying_t_1": 4137.23,
                    "Option_PnL": 0.012850859334475823,
                    "Delta_PnL": 0.009810640573320357,
                    "Total_PnL": 0.003040218761155466,
                    "delta_t": 0.42167967105159826,
                    "option_price_t": 98.09,
                    "underlying_price_t": 4117.37
                },
                "put": {
                    "start_date": "2023-10-24",
                    "strike": 4200,
                    "maturity": "2024-01-19",
                    "units": -0.0011078327012479163,
                    "gamma": 0.0011194128663858977,
                    "vega": 814.3220914398405,
                    "tau": 0.23835616438356164,
                    "delta_t_1": -0.554093359206499,
                    "option_price_t_1": 172.46,
                    "underlying_t_1": 4137.23,
                    "Option_PnL": -0.009150698112307778,
                    "Delta_PnL": -0.012190916873462897,
                    "Total_PnL": 0.003040218761155119,
                    "delta_t": -0.5783203289484018,
                    "option_price_t": 180.72,
                    "underlying_price_t": 4117.37
                }
            },
            "sv_2023-10-25_2024-01-19": {
                "call": {
                    "start_date": "2023-10-25",
                    "strike": 4250,
                    "maturity": "2024-01-19",
                    "units": -0.0011152315928321368,
                    "gamma": 0.0011177898105281013,
                    "vega": 803.3811185054147,
                    "tau": 0.2356164383561644,
                    "delta_t_1": 0.3904336777630854,
                    "option_price_t_1": 90.45,
                    "underlying_t_1": 4137.23,
                    "Option_PnL": 0.01159840856545423,
                    "Delta_PnL": 0.008647520090811971,
                    "Total_PnL": 0.0029508884746422583,
                    "delta_t": 0.3659939852956634,
                    "option_price_t": 80.05,
                    "underlying_price_t": 4117.37
                },
                "put": {
                    "start_date": "2023-10-25",
                    "strike": 4250,
                    "maturity": "2024-01-19",
                    "units": -0.0011152315928321368,
                    "gamma": 0.0011177898105281013,
                    "vega": 803.3811185054147,
                    "tau": 0.2356164383561644,
                    "delta_t_1": -0.6095663222369145,
                    "option_price_t_1": 203.22,
                    "underlying_t_1": 4137.23,
                    "Option_PnL": -0.010550090868192023,
                    "Delta_PnL": -0.013500979342833898,
                    "Total_PnL": 0.002950888474641875,
                    "delta_t": -0.6340060147043366,
                    "option_price_t": 212.68,
                    "underlying_price_t": 4117.37
                }
            },
            "sv_2023-10-26_2024-01-19": {
                "call": {
                    "start_date": "2023-10-26",
                    "strike": 4200,
                    "maturity": "2024-01-19",
                    "units": -0.0011316454648871415,
                    "gamma": 0.001143769603780592,
                    "vega": 788.882599857991,
                    "tau": 0.2328767123287671,
                    "delta_t_1": 0.44488972077612554,
                    "option_price_t_1": 109.69,
                    "underlying_t_1": 4186.77,
                    "delta_t": 0.420397881911207,
                    "option_price_t": 98.09,
                    "underlying_price_t": 4117.37,
                    "Option_PnL": 0.013127087392690836,
                    "Delta_PnL": 0.03493994598145019,
                    "Total_PnL": -0.021812858588759358
                },
                "put": {
                    "start_date": "2023-10-26",
                    "strike": 4200,
                    "maturity": "2024-01-19",
                    "units": -0.0011316454648871415,
                    "gamma": 0.001143769603780592,
                    "vega": 788.882599857991,
                    "tau": 0.2328767123287671,
                    "delta_t_1": -0.5551102792238745,
                    "option_price_t_1": 172.46,
                    "underlying_t_1": 4186.77,
                    "delta_t": -0.5796021180887929,
                    "option_price_t": 180.72,
                    "underlying_price_t": 4117.37,
                    "Option_PnL": -0.009347391539967779,
                    "Delta_PnL": -0.04359624928171805,
                    "Total_PnL": 0.034248857741750266
                }
            },
            "sv_2023-10-27_2024-01-19": {
                "call": {
                    "start_date": "2023-10-27",
                    "strike": 4150,
                    "maturity": "2024-01-19",
                    "units": -0.001134655966802693,
                    "delta_t": 0.47772498387408785,
                    "gamma": 0.0011849311129519186,
                    "vega": 786.7658425192644,
                    "tau": 0.23013698630136986,
                    "option_price_t": 118.91,
                    "underlying_price_t": 4137.23
                },
                "put": {
                    "start_date": "2023-10-27",
                    "strike": 4150,
                    "maturity": "2024-01-19",
                    "units": -0.001134655966802693,
                    "delta_t": -0.5222750161259122,
                    "gamma": 0.0011849311129519186,
                    "vega": 786.7658425192644,
                    "tau": 0.23013698630136986,
                    "option_price_t": 151.54,
                    "underlying_price_t": 4137.23
                }
            }
        }
    }
}