{
    "SPX_Straddle_Volatility_Capture": {
        "date": "2024-07-09",
        "index_levels": 121.94546541479097,
        "result": {
            "sv_2024-04-22_2024-07-19": {
                "call": {
                    "start_date": "2024-04-22",
                    "strike": 4950,
                    "maturity": "2024-07-19",
                    "units": -0.0009773208530843484,
                    "gamma": 0.001042382510748607,
                    "vega": 962.083017255965,
                    "tau": 0.2410958904109589,
                    "delta_t_1": 0.9839043058236058,
                    "option_price_t_1": 622.85,
                    "underlying_t_1": 5572.85,
                    "Option_PnL": -0.004036335123238355,
                    "Delta_PnL": -0.003971367507500506,
                    "Total_PnL": -6.49676157378487e-05,
                    "delta_t": 0.9878452680489371,
                    "option_price_t": 626.98,
                    "underlying_price_t": 5576.98
                },
                "put": {
                    "start_date": "2024-04-22",
                    "strike": 4950,
                    "maturity": "2024-07-19",
                    "units": -0.0009773208530843484,
                    "gamma": 0.001042382510748607,
                    "vega": 962.083017255965,
                    "tau": 0.2410958904109589,
                    "delta_t_1": -0.016095694176394226,
                    "option_price_t_1": 0.01,
                    "underlying_t_1": 5572.85,
                    "Option_PnL": -0.0,
                    "Delta_PnL": 6.496761573707053e-05,
                    "Total_PnL": -6.496761573707053e-05,
                    "delta_t": -0.01215473195106287,
                    "option_price_t": 0.01,
                    "underlying_price_t": 5576.98
                }
            },
            "sv_2024-04-23_2024-07-19": {
                "call": {
                    "start_date": "2024-04-23",
                    "strike": 5000,
                    "maturity": "2024-07-19",
                    "units": -0.0009735985352834306,
                    "gamma": 0.0009938422209287844,
                    "vega": 963.989674679371,
                    "tau": 0.23835616438356164,
                    "delta_t_1": 0.9757914034662916,
                    "option_price_t_1": 572.85,
                    "underlying_t_1": 5572.85,
                    "Option_PnL": -0.004020961950720564,
                    "Delta_PnL": -0.003923620105177421,
                    "Total_PnL": -9.734184554314324e-05,
                    "delta_t": 0.9810616972060965,
                    "option_price_t": 576.98,
                    "underlying_price_t": 5576.98
                },
                "put": {
                    "start_date": "2024-04-23",
                    "strike": 5000,
                    "maturity": "2024-07-19",
                    "units": -0.0009735985352834306,
                    "gamma": 0.0009938422209287844,
                    "vega": 963.989674679371,
                    "tau": 0.23835616438356164,
                    "delta_t_1": -0.024208596533708437,
                    "option_price_t_1": 0.01,
                    "underlying_t_1": 5572.85,
                    "Option_PnL": -0.0,
                    "Delta_PnL": 9.734184554236861e-05,
                    "Total_PnL": -9.734184554236861e-05,
                    "delta_t": -0.018938302793903516,
                    "option_price_t": 0.01,
                    "underlying_price_t": 5576.98
                }
            },
            "sv_2024-04-24_2024-07-19": {
                "call": {
                    "start_date": "2024-04-24",
                    "strike": 5050,
                    "maturity": "2024-07-19",
                    "units": -0.000963339415282953,
                    "gamma": 0.0010529471488420694,
                    "vega": 977.7209300639571,
                    "tau": 0.2356164383561644,
                    "delta_t_1": 0.9644841256178123,
                    "option_price_t_1": 522.85,
                    "underlying_t_1": 5572.85,
                    "Option_PnL": -0.003978591785118592,
                    "Delta_PnL": -0.0038372886190595765,
                    "Total_PnL": -0.00014130316605901524,
                    "delta_t": 0.9712896185528735,
                    "option_price_t": 526.98,
                    "underlying_price_t": 5576.98
                },
                "put": {
                    "start_date": "2024-04-24",
                    "strike": 5050,
                    "maturity": "2024-07-19",
                    "units": -0.000963339415282953,
                    "gamma": 0.0010529471488420694,
                    "vega": 977.7209300639571,
                    "tau": 0.2356164383561644,
                    "delta_t_1": -0.03551587438218773,
                    "option_price_t_1": 0.01,
                    "underlying_t_1": 5572.85,
                    "Option_PnL": -0.0,
                    "Delta_PnL": 0.0001413031660582487,
                    "Total_PnL": -0.0001413031660582487,
                    "delta_t": -0.028710381447126454,
                    "option_price_t": 0.01,
                    "underlying_price_t": 5576.98
                }
            },
            "sv_2024-04-25_2024-07-19": {
                "call": {
                    "start_date": "2024-04-25",
                    "strike": 5050,
                    "maturity": "2024-07-19",
                    "units": -0.0009696217237000927,
                    "gamma": 0.0010645988830577874,
                    "vega": 971.3905501669482,
                    "tau": 0.2328767123287671,
                    "delta_t_1": 0.9652794042738313,
                    "option_price_t_1": 522.85,
                    "underlying_t_1": 5572.85,
                    "Option_PnL": -0.004004537718881379,
                    "Delta_PnL": -0.0038654977836731596,
                    "Total_PnL": -0.00013903993520821912,
                    "delta_t": 0.9719931275568308,
                    "option_price_t": 526.98,
                    "underlying_price_t": 5576.98
                },
                "put": {
                    "start_date": "2024-04-25",
                    "strike": 5050,
                    "maturity": "2024-07-19",
                    "units": -0.0009696217237000927,
                    "gamma": 0.0010645988830577874,
                    "vega": 971.3905501669482,
                    "tau": 0.2328767123287671,
                    "delta_t_1": -0.0347205957261687,
                    "option_price_t_1": 0.01,
                    "underlying_t_1": 5572.85,
                    "Option_PnL": -0.0,
                    "Delta_PnL": 0.00013903993520744735,
                    "Total_PnL": -0.00013903993520744735,
                    "delta_t": -0.02800687244316924,
                    "option_price_t": 0.01,
                    "underlying_price_t": 5576.98
                }
            },
            "sv_2024-04-26_2024-07-19": {
                "call": {
                    "start_date": "2024-04-26",
                    "strike": 5050,
                    "maturity": "2024-07-19",
                    "units": -0.0009773266770969396,
                    "gamma": 0.0010186895453930507,
                    "vega": 962.3880532768436,
                    "tau": 0.23013698630136986,
                    "delta_t_1": 0.9660739114465642,
                    "option_price_t_1": 522.85,
                    "underlying_t_1": 5572.85,
                    "Option_PnL": -0.004036359176410357,
                    "Delta_PnL": -0.0038994212975572338,
                    "Total_PnL": -0.00013693787885312282,
                    "delta_t": 0.9726944762899821,
                    "option_price_t": 526.98,
                    "underlying_price_t": 5576.98
                },
                "put": {
                    "start_date": "2024-04-26",
                    "strike": 5050,
                    "maturity": "2024-07-19",
                    "units": -0.0009773266770969396,
                    "gamma": 0.0010186895453930507,
                    "vega": 962.3880532768436,
                    "tau": 0.23013698630136986,
                    "delta_t_1": -0.03392608855343582,
                    "option_price_t_1": 0.01,
                    "underlying_t_1": 5572.85,
                    "Option_PnL": -0.0,
                    "Delta_PnL": 0.00013693787885234464,
                    "Total_PnL": -0.00013693787885234464,
                    "delta_t": -0.02730552371001793,
                    "option_price_t": 0.01,
                    "underlying_price_t": 5576.98
                }
            },
            "sv_2024-04-29_2024-07-19": {
                "call": {
                    "start_date": "2024-04-29",
                    "strike": 5100,
                    "maturity": "2024-07-19",
                    "units": -0.0009851369263919414,
                    "gamma": 0.0010526004170745228,
                    "vega": 958.448192653521,
                    "tau": 0.2219178082191781,
                    "delta_t_1": 0.9530651844569827,
                    "option_price_t_1": 472.85,
                    "underlying_t_1": 5572.85,
                    "Option_PnL": -0.004068615505998714,
                    "Delta_PnL": -0.003877655787708457,
                    "Total_PnL": -0.0001909597182902568,
                    "delta_t": 0.9611886365511702,
                    "option_price_t": 476.98,
                    "underlying_price_t": 5576.98
                },
                "put": {
                    "start_date": "2024-04-29",
                    "strike": 5100,
                    "maturity": "2024-07-19",
                    "units": -0.0009851369263919414,
                    "gamma": 0.0010526004170745228,
                    "vega": 958.448192653521,
                    "tau": 0.2219178082191781,
                    "delta_t_1": -0.04693481554301726,
                    "option_price_t_1": 0.01,
                    "underlying_t_1": 5572.85,
                    "Option_PnL": -0.0,
                    "Delta_PnL": 0.00019095971828947267,
                    "Total_PnL": -0.00019095971828947267,
                    "delta_t": -0.03881136344882985,
                    "option_price_t": 0.01,
                    "underlying_price_t": 5576.98
                }
            },
            "sv_2024-04-30_2024-07-19": {
                "call": {
                    "start_date": "2024-04-30",
                    "strike": 5100,
                    "maturity": "2024-07-19",
                    "units": -0.0010053155085321317,
                    "gamma": 0.0010247546645768952,
                    "vega": 932.9488541315619,
                    "tau": 0.2191780821917808,
                    "delta_t_1": 0.9540475214798904,
                    "option_price_t_1": 472.85,
                    "underlying_t_1": 5572.85,
                    "Option_PnL": -0.004151953050237699,
                    "Delta_PnL": -0.003961160516879385,
                    "Total_PnL": -0.0001907925333583145,
                    "delta_t": 0.9620778586536852,
                    "option_price_t": 476.98,
                    "underlying_price_t": 5576.98
                },
                "put": {
                    "start_date": "2024-04-30",
                    "strike": 5100,
                    "maturity": "2024-07-19",
                    "units": -0.0010053155085321317,
                    "gamma": 0.0010247546645768952,
                    "vega": 932.9488541315619,
                    "tau": 0.2191780821917808,
                    "delta_t_1": -0.04595247852010964,
                    "option_price_t_1": 0.01,
                    "underlying_t_1": 5572.85,
                    "Option_PnL": -0.0,
                    "Delta_PnL": 0.00019079253335751482,
                    "Total_PnL": -0.00019079253335751482,
                    "delta_t": -0.037922141346314775,
                    "option_price_t": 0.01,
                    "underlying_price_t": 5576.98
                }
            },
            "sv_2024-05-01_2024-07-19": {
                "call": {
                    "start_date": "2024-05-01",
                    "strike": 5050,
                    "maturity": "2024-07-19",
                    "units": -0.0010090373111634287,
                    "gamma": 0.001050280643878207,
                    "vega": 930.4590016552264,
                    "tau": 0.21643835616438356,
                    "delta_t_1": 0.9700279276228058,
                    "option_price_t_1": 522.85,
                    "underlying_t_1": 5572.85,
                    "Option_PnL": -0.004167324095104956,
                    "Delta_PnL": -0.004042420755706466,
                    "Total_PnL": -0.0001249033393984902,
                    "delta_t": 0.9761616896976923,
                    "option_price_t": 526.98,
                    "underlying_price_t": 5576.98
                },
                "put": {
                    "start_date": "2024-05-01",
                    "strike": 5050,
                    "maturity": "2024-07-19",
                    "units": -0.0010090373111634287,
                    "gamma": 0.001050280643878207,
                    "vega": 930.4590016552264,
                    "tau": 0.21643835616438356,
                    "delta_t_1": -0.029972072377194237,
                    "option_price_t_1": 0.01,
                    "underlying_t_1": 5572.85,
                    "Option_PnL": -0.0,
                    "Delta_PnL": 0.00012490333939768714,
                    "Total_PnL": -0.00012490333939768714,
                    "delta_t": -0.023838310302307653,
                    "option_price_t": 0.01,
                    "underlying_price_t": 5576.98
                }
            },
            "sv_2024-05-02_2024-07-19": {
                "call": {
                    "start_date": "2024-05-02",
                    "strike": 5000,
                    "maturity": "2024-07-19",
                    "units": -0.0010289933115839236,
                    "gamma": 0.0010252294417133086,
                    "vega": 914.1026510418757,
                    "tau": 0.2136986301369863,
                    "delta_t_1": 0.9813014394007246,
                    "option_price_t_1": 572.85,
                    "underlying_t_1": 5572.85,
                    "Option_PnL": -0.0042497423768415995,
                    "Delta_PnL": -0.004170278311476114,
                    "Total_PnL": -7.946406536548517e-05,
                    "delta_t": 0.9857301812508373,
                    "option_price_t": 576.98,
                    "underlying_price_t": 5576.98
                },
                "put": {
                    "start_date": "2024-05-02",
                    "strike": 5000,
                    "maturity": "2024-07-19",
                    "units": -0.0010289933115839236,
                    "gamma": 0.0010252294417133086,
                    "vega": 914.1026510418757,
                    "tau": 0.2136986301369863,
                    "delta_t_1": -0.018698560599275438,
                    "option_price_t_1": 0.01,
                    "underlying_t_1": 5572.85,
                    "Option_PnL": -0.0,
                    "Delta_PnL": 7.946406536466618e-05,
                    "Total_PnL": -7.946406536466618e-05,
                    "delta_t": -0.014269818749162666,
                    "option_price_t": 0.01,
                    "underlying_price_t": 5576.98
                }
            },
            "sv_2024-05-03_2024-07-19": {
                "call": {
                    "start_date": "2024-05-03",
                    "strike": 5050,
                    "maturity": "2024-07-19",
                    "units": -0.0010266281655617825,
                    "gamma": 0.0009788205139728038,
                    "vega": 913.6962828748897,
                    "tau": 0.21095890410958903,
                    "delta_t_1": 0.9715968161943243,
                    "option_price_t_1": 522.85,
                    "underlying_t_1": 5572.85,
                    "Option_PnL": -0.004239974323770157,
                    "Delta_PnL": -0.004119545553719974,
                    "Total_PnL": -0.00012042877005018302,
                    "delta_t": 0.9775260140905574,
                    "option_price_t": 526.98,
                    "underlying_price_t": 5576.98
                },
                "put": {
                    "start_date": "2024-05-03",
                    "strike": 5050,
                    "maturity": "2024-07-19",
                    "units": -0.0010266281655617825,
                    "gamma": 0.0009788205139728038,
                    "vega": 913.6962828748897,
                    "tau": 0.21095890410958903,
                    "delta_t_1": -0.028403183805675747,
                    "option_price_t_1": 0.01,
                    "underlying_t_1": 5572.85,
                    "Option_PnL": -0.0,
                    "Delta_PnL": 0.00012042877004936629,
                    "Total_PnL": -0.00012042877004936629,
                    "delta_t": -0.022473985909442606,
                    "option_price_t": 0.01,
                    "underlying_price_t": 5576.98
                }
            },
            "sv_2024-05-06_2024-07-19": {
                "call": {
                    "start_date": "2024-05-06",
                    "strike": 5150,
                    "maturity": "2024-07-19",
                    "units": -0.0010148269166732804,
                    "gamma": 0.0009867932720268799,
                    "vega": 924.4276212626899,
                    "tau": 0.20273972602739726,
                    "delta_t_1": 0.9406884501651653,
                    "option_price_t_1": 422.85,
                    "underlying_t_1": 5572.85,
                    "Option_PnL": -0.0041912351658606435,
                    "Delta_PnL": -0.003942646512450429,
                    "Total_PnL": -0.00024858865341021493,
                    "delta_t": 0.9500537599720188,
                    "option_price_t": 426.98,
                    "underlying_price_t": 5576.98
                },
                "put": {
                    "start_date": "2024-05-06",
                    "strike": 5150,
                    "maturity": "2024-07-19",
                    "units": -0.0010148269166732804,
                    "gamma": 0.0009867932720268799,
                    "vega": 924.4276212626899,
                    "tau": 0.20273972602739726,
                    "delta_t_1": -0.059311549834834665,
                    "option_price_t_1": 0.01,
                    "underlying_t_1": 5572.85,
                    "Option_PnL": -0.0,
                    "Delta_PnL": 0.0002485886534094072,
                    "Total_PnL": -0.0002485886534094072,
                    "delta_t": -0.049946240027981204,
                    "option_price_t": 0.01,
                    "underlying_price_t": 5576.98
                }
            },
            "sv_2024-05-07_2024-07-19": {
                "call": {
                    "start_date": "2024-05-07",
                    "strike": 5200,
                    "maturity": "2024-07-19",
                    "units": -0.0010149724515034104,
                    "gamma": 0.0009998027806903409,
                    "vega": 925.5228622331686,
                    "tau": 0.2,
                    "delta_t_1": 0.9164627875129898,
                    "option_price_t_1": 372.86,
                    "underlying_t_1": 5572.85,
                    "Option_PnL": -0.004181686500194056,
                    "Delta_PnL": -0.003841661911294071,
                    "Total_PnL": -0.00034002458889998474,
                    "delta_t": 0.927623940424953,
                    "option_price_t": 376.98,
                    "underlying_price_t": 5576.98
                },
                "put": {
                    "start_date": "2024-05-07",
                    "strike": 5200,
                    "maturity": "2024-07-19",
                    "units": -0.0010149724515034104,
                    "gamma": 0.0009998027806903409,
                    "vega": 925.5228622331686,
                    "tau": 0.2,
                    "delta_t_1": -0.08353721248701018,
                    "option_price_t_1": 0.01,
                    "underlying_t_1": 5572.85,
                    "Option_PnL": -0.0,
                    "Delta_PnL": 0.00035017431341420157,
                    "Total_PnL": -0.00035017431341420157,
                    "delta_t": -0.072376059575047,
                    "option_price_t": 0.01,
                    "underlying_price_t": 5576.98
                }
            },
            "sv_2024-05-08_2024-07-19": {
                "call": {
                    "start_date": "2024-05-08",
                    "strike": 5200,
                    "maturity": "2024-07-19",
                    "units": -0.0010236629681825858,
                    "gamma": 0.0010080899360472345,
                    "vega": 919.1608532756069,
                    "tau": 0.19726027397260273,
                    "delta_t_1": 0.9178683584688214,
                    "option_price_t_1": 372.86,
                    "underlying_t_1": 5572.85,
                    "Option_PnL": -0.0042174914289122584,
                    "Delta_PnL": -0.0038804978131935734,
                    "Total_PnL": -0.0003369936157186851,
                    "delta_t": 0.9289582854071397,
                    "option_price_t": 376.98,
                    "underlying_price_t": 5576.98
                },
                "put": {
                    "start_date": "2024-05-08",
                    "strike": 5200,
                    "maturity": "2024-07-19",
                    "units": -0.0010236629681825858,
                    "gamma": 0.0010080899360472345,
                    "vega": 919.1608532756069,
                    "tau": 0.19726027397260273,
                    "delta_t_1": -0.08213164153117858,
                    "option_price_t_1": 0.01,
                    "underlying_t_1": 5572.85,
                    "Option_PnL": -0.0,
                    "Delta_PnL": 0.0003472302453996872,
                    "Total_PnL": -0.0003472302453996872,
                    "delta_t": -0.07104171459286035,
                    "option_price_t": 0.01,
                    "underlying_price_t": 5576.98
                }
            },
            "sv_2024-05-09_2024-07-19": {
                "call": {
                    "start_date": "2024-05-09",
                    "strike": 5200,
                    "maturity": "2024-07-19",
                    "units": -0.001029094727361042,
                    "gamma": 0.0010169839697854116,
                    "vega": 914.9464529624144,
                    "tau": 0.19452054794520549,
                    "delta_t_1": 0.919285433109919,
                    "option_price_t_1": 372.86,
                    "underlying_t_1": 5572.85,
                    "Option_PnL": -0.0042398702767274974,
                    "Delta_PnL": -0.003907111301592081,
                    "Total_PnL": -0.0003327589751354167,
                    "delta_t": 0.9303014619719377,
                    "option_price_t": 376.98,
                    "underlying_price_t": 5576.98
                },
                "put": {
                    "start_date": "2024-05-09",
                    "strike": 5200,
                    "maturity": "2024-07-19",
                    "units": -0.001029094727361042,
                    "gamma": 0.0010169839697854116,
                    "vega": 914.9464529624144,
                    "tau": 0.19452054794520549,
                    "delta_t_1": -0.08071456689008105,
                    "option_price_t_1": 0.01,
                    "underlying_t_1": 5572.85,
                    "Option_PnL": -0.0,
                    "Delta_PnL": 0.00034304992240819936,
                    "Total_PnL": -0.00034304992240819936,
                    "delta_t": -0.06969853802806225,
                    "option_price_t": 0.01,
                    "underlying_price_t": 5576.98
                }
            },
            "sv_2024-05-10_2024-07-19": {
                "call": {
                    "start_date": "2024-05-10",
                    "strike": 5200,
                    "maturity": "2024-07-19",
                    "units": -0.0010375355910559705,
                    "gamma": 0.0010202859346853128,
                    "vega": 908.2784580910354,
                    "tau": 0.1917808219178082,
                    "delta_t_1": 0.9207139998456197,
                    "option_price_t_1": 372.86,
                    "underlying_t_1": 5572.85,
                    "Option_PnL": -0.004274646635150603,
                    "Delta_PnL": -0.003945279736815596,
                    "Total_PnL": -0.0003293668983350073,
                    "delta_t": 0.9316533699087736,
                    "option_price_t": 376.98,
                    "underlying_price_t": 5576.98
                },
                "put": {
                    "start_date": "2024-05-10",
                    "strike": 5200,
                    "maturity": "2024-07-19",
                    "units": -0.0010375355910559705,
                    "gamma": 0.0010202859346853128,
                    "vega": 908.2784580910354,
                    "tau": 0.1917808219178082,
                    "delta_t_1": -0.07928600015438025,
                    "option_price_t_1": 0.01,
                    "underlying_t_1": 5572.85,
                    "Option_PnL": -0.0,
                    "Delta_PnL": 0.0003397422542447319,
                    "Total_PnL": -0.0003397422542447319,
                    "delta_t": -0.06834663009122643,
                    "option_price_t": 0.01,
                    "underlying_price_t": 5576.98
                }
            },
            "sv_2024-05-13_2024-07-19": {
                "call": {
                    "start_date": "2024-05-13",
                    "strike": 5200,
                    "maturity": "2024-07-19",
                    "units": -0.0010653645881514154,
                    "gamma": 0.0010441013678797598,
                    "vega": 888.6231807139926,
                    "tau": 0.18356164383561643,
                    "delta_t_1": 0.9250683411095729,
                    "option_price_t_1": 372.86,
                    "underlying_t_1": 5572.85,
                    "Option_PnL": -0.004389302103183837,
                    "Delta_PnL": -0.004070259765742619,
                    "Total_PnL": -0.0003190423374412176,
                    "delta_t": 0.9357602411032822,
                    "option_price_t": 376.98,
                    "underlying_price_t": 5576.98
                },
                "put": {
                    "start_date": "2024-05-13",
                    "strike": 5200,
                    "maturity": "2024-07-19",
                    "units": -0.0010653645881514154,
                    "gamma": 0.0010441013678797598,
                    "vega": 888.6231807139926,
                    "tau": 0.18356164383561643,
                    "delta_t_1": -0.07493165889042708,
                    "option_price_t_1": 0.01,
                    "underlying_t_1": 5572.85,
                    "Option_PnL": -0.0,
                    "Delta_PnL": 0.00032969598332187414,
                    "Total_PnL": -0.00032969598332187414,
                    "delta_t": -0.06423975889671785,
                    "option_price_t": 0.01,
                    "underlying_price_t": 5576.98
                }
            },
            "sv_2024-05-14_2024-07-19": {
                "call": {
                    "start_date": "2024-05-14",
                    "strike": 5200,
                    "maturity": "2024-07-19",
                    "units": -0.0010765244910136025,
                    "gamma": 0.0010443903098311127,
                    "vega": 878.7029201774931,
                    "tau": 0.18082191780821918,
                    "delta_t_1": 0.9265424908634672,
                    "option_price_t_1": 372.86,
                    "underlying_t_1": 5572.85,
                    "Option_PnL": -0.004435280902976047,
                    "Delta_PnL": -0.004119450672355585,
                    "Total_PnL": -0.0003158302306204624,
                    "delta_t": 0.9371457451473698,
                    "option_price_t": 376.98,
                    "underlying_price_t": 5576.98
                },
                "put": {
                    "start_date": "2024-05-14",
                    "strike": 5200,
                    "maturity": "2024-07-19",
                    "units": -0.0010765244910136025,
                    "gamma": 0.0010443903098311127,
                    "vega": 878.7029201774931,
                    "tau": 0.18082191780821918,
                    "delta_t_1": -0.07345750913653282,
                    "option_price_t_1": 0.01,
                    "underlying_t_1": 5572.85,
                    "Option_PnL": -0.0,
                    "Delta_PnL": 0.00032659547552973224,
                    "Total_PnL": -0.00032659547552973224,
                    "delta_t": -0.06285425485263019,
                    "option_price_t": 0.01,
                    "underlying_price_t": 5576.98
                }
            },
            "sv_2024-05-15_2024-07-19": {
                "call": {
                    "start_date": "2024-05-15",
                    "strike": 5250,
                    "maturity": "2024-07-19",
                    "units": -0.001067291648198817,
                    "gamma": 0.0010105205041074674,
                    "vega": 878.1088647068583,
                    "tau": 0.1780821917808219,
                    "delta_t_1": 0.8966435179818504,
                    "option_price_t_1": 322.89,
                    "underlying_t_1": 5572.85,
                    "Option_PnL": -0.004375895757615174,
                    "Delta_PnL": -0.003952327970573745,
                    "Total_PnL": -0.0004235677870414291,
                    "delta_t": 0.909037922837705,
                    "option_price_t": 326.99,
                    "underlying_price_t": 5576.98
                },
                "put": {
                    "start_date": "2024-05-15",
                    "strike": 5250,
                    "maturity": "2024-07-19",
                    "units": -0.001067291648198817,
                    "gamma": 0.0010105205041074674,
                    "vega": 878.1088647068583,
                    "tau": 0.1780821917808219,
                    "delta_t_1": -0.10335648201814962,
                    "option_price_t_1": 0.04,
                    "underlying_t_1": 5572.85,
                    "Option_PnL": 3.201874944596451e-05,
                    "Delta_PnL": 0.0004555865364865146,
                    "Total_PnL": -0.0004235677870405501,
                    "delta_t": -0.09096207716229499,
                    "option_price_t": 0.01,
                    "underlying_price_t": 5576.98
                }
            },
            "sv_2024-05-16_2024-07-19": {
                "call": {
                    "start_date": "2024-05-16",
                    "strike": 5300,
                    "maturity": "2024-07-19",
                    "units": -0.0010645465901307422,
                    "gamma": 0.001072398647643029,
                    "vega": 884.565291521436,
                    "tau": 0.17534246575342466,
                    "delta_t_1": 0.8585564413608313,
                    "option_price_t_1": 273.05,
                    "underlying_t_1": 5572.85,
                    "Option_PnL": -0.004258186360522969,
                    "Delta_PnL": -0.003774709861512208,
                    "Total_PnL": -0.0004834764990107607,
                    "delta_t": 0.8723313342864359,
                    "option_price_t": 277.05,
                    "underlying_price_t": 5576.98
                },
                "put": {
                    "start_date": "2024-05-16",
                    "strike": 5300,
                    "maturity": "2024-07-19",
                    "units": -0.0010645465901307422,
                    "gamma": 0.001072398647643029,
                    "vega": 884.565291521436,
                    "tau": 0.17534246575342466,
                    "delta_t_1": -0.1414435586391687,
                    "option_price_t_1": 0.2,
                    "underlying_t_1": 5572.85,
                    "Option_PnL": 0.0001383910567169965,
                    "Delta_PnL": 0.0006218675557269054,
                    "Total_PnL": -0.00048347649900990885,
                    "delta_t": -0.12766866571356406,
                    "option_price_t": 0.07,
                    "underlying_price_t": 5576.98
                }
            },
            "sv_2024-05-17_2024-07-19": {
                "call": {
                    "start_date": "2024-05-17",
                    "strike": 5300,
                    "maturity": "2024-07-19",
                    "units": -0.0010752624574704422,
                    "gamma": 0.0011028276011611343,
                    "vega": 878.1603140637321,
                    "tau": 0.1726027397260274,
                    "delta_t_1": 0.86036682126855,
                    "option_price_t_1": 273.05,
                    "underlying_t_1": 5572.85,
                    "Option_PnL": -0.004301049829881769,
                    "Delta_PnL": -0.003820746188785498,
                    "Total_PnL": -0.00048030364109627076,
                    "delta_t": 0.8741258110259992,
                    "option_price_t": 277.05,
                    "underlying_price_t": 5576.98
                },
                "put": {
                    "start_date": "2024-05-17",
                    "strike": 5300,
                    "maturity": "2024-07-19",
                    "units": -0.0010752624574704422,
                    "gamma": 0.0011028276011611343,
                    "vega": 878.1603140637321,
                    "tau": 0.1726027397260274,
                    "delta_t_1": -0.13963317873144998,
                    "option_price_t_1": 0.2,
                    "underlying_t_1": 5572.85,
                    "Option_PnL": 0.0001397841194711575,
                    "Delta_PnL": 0.0006200877605665679,
                    "Total_PnL": -0.00048030364109541044,
                    "delta_t": -0.12587418897400082,
                    "option_price_t": 0.07,
                    "underlying_price_t": 5576.98
                }
            },
            "sv_2024-05-20_2024-08-16": {
                "call": {
                    "start_date": "2024-05-20",
                    "strike": 5300,
                    "maturity": "2024-08-16",
                    "units": -0.0009119153231014059,
                    "gamma": 0.0009316863255701578,
                    "vega": 1037.965658202185,
                    "tau": 0.2410958904109589,
                    "delta_t_1": 0.822109141155912,
                    "option_price_t_1": 281.23,
                    "underlying_t_1": 5572.85,
                    "Option_PnL": -0.0018967838720509098,
                    "Delta_PnL": -0.003096235902327287,
                    "Total_PnL": 0.001199452030276377,
                    "delta_t": 0.8358031989480794,
                    "option_price_t": 283.31,
                    "underlying_price_t": 5576.98
                },
                "put": {
                    "start_date": "2024-05-20",
                    "strike": 5300,
                    "maturity": "2024-08-16",
                    "units": -0.0009119153231014059,
                    "gamma": 0.0009316863255701578,
                    "vega": 1037.965658202185,
                    "tau": 0.2410958904109589,
                    "delta_t_1": -0.17789085884408795,
                    "option_price_t_1": 8.38,
                    "underlying_t_1": 5572.85,
                    "Option_PnL": 0.0018694264123578826,
                    "Delta_PnL": 0.0006699743820807895,
                    "Total_PnL": 0.001199452030277093,
                    "delta_t": -0.16419680105192058,
                    "option_price_t": 6.33,
                    "underlying_price_t": 5576.98
                }
            },
            "sv_2024-05-21_2024-08-16": {
                "call": {
                    "start_date": "2024-05-21",
                    "strike": 5300,
                    "maturity": "2024-08-16",
                    "units": -0.0009173031404324595,
                    "gamma": 0.0009319769188125502,
                    "vega": 1032.2294501606552,
                    "tau": 0.23835616438356164,
                    "delta_t_1": 0.8234010624960861,
                    "option_price_t_1": 281.23,
                    "underlying_t_1": 5572.85,
                    "Option_PnL": -0.001907990532099501,
                    "Delta_PnL": -0.003119423611311931,
                    "Total_PnL": 0.0012114330792124298,
                    "delta_t": 0.8371099780247282,
                    "option_price_t": 283.31,
                    "underlying_price_t": 5576.98
                },
                "put": {
                    "start_date": "2024-05-21",
                    "strike": 5300,
                    "maturity": "2024-08-16",
                    "units": -0.0009173031404324595,
                    "gamma": 0.0009319769188125502,
                    "vega": 1032.2294501606552,
                    "tau": 0.23835616438356164,
                    "delta_t_1": -0.17659893750391387,
                    "option_price_t_1": 8.38,
                    "underlying_t_1": 5572.85,
                    "Option_PnL": 0.0018804714378865424,
                    "Delta_PnL": 0.0006690383586733925,
                    "Total_PnL": 0.00121143307921315,
                    "delta_t": -0.1628900219752718,
                    "option_price_t": 6.33,
                    "underlying_price_t": 5576.98
                }
            },
            "sv_2024-05-22_2024-08-16": {
                "call": {
                    "start_date": "2024-05-22",
                    "strike": 5300,
                    "maturity": "2024-08-16",
                    "units": -0.000925414295775666,
                    "gamma": 0.0009618633831897737,
                    "vega": 1026.0839578595762,
                    "tau": 0.2356164383561644,
                    "delta_t_1": 0.824709826230686,
                    "option_price_t_1": 281.23,
                    "underlying_t_1": 5572.85,
                    "Option_PnL": -0.0019248617352133704,
                    "Delta_PnL": -0.003152008826439428,
                    "Total_PnL": 0.0012271470912260578,
                    "delta_t": 0.8384329595052911,
                    "option_price_t": 283.31,
                    "underlying_price_t": 5576.98
                },
                "put": {
                    "start_date": "2024-05-22",
                    "strike": 5300,
                    "maturity": "2024-08-16",
                    "units": -0.000925414295775666,
                    "gamma": 0.0009618633831897737,
                    "vega": 1026.0839578595762,
                    "tau": 0.2356164383561644,
                    "delta_t_1": -0.175290173769314,
                    "option_price_t_1": 8.38,
                    "underlying_t_1": 5572.85,
                    "Option_PnL": 0.0018970993063401158,
                    "Delta_PnL": 0.0006699522151133315,
                    "Total_PnL": 0.0012271470912267844,
                    "delta_t": -0.16156704049470894,
                    "option_price_t": 6.33,
                    "underlying_price_t": 5576.98
                }
            },
            "sv_2024-05-23_2024-08-16": {
                "call": {
                    "start_date": "2024-05-23",
                    "strike": 5300,
                    "maturity": "2024-08-16",
                    "units": -0.0009380874160014231,
                    "gamma": 0.0009711048845371756,
                    "vega": 1013.3814838594814,
                    "tau": 0.2328767123287671,
                    "delta_t_1": 0.82603577302067,
                    "option_price_t_1": 281.23,
                    "underlying_t_1": 5572.85,
                    "Option_PnL": -0.001951221825282945,
                    "Delta_PnL": -0.003200311244649074,
                    "Total_PnL": 0.001249089419366129,
                    "delta_t": 0.8397724480950257,
                    "option_price_t": 283.31,
                    "underlying_price_t": 5576.98
                },
                "put": {
                    "start_date": "2024-05-23",
                    "strike": 5300,
                    "maturity": "2024-08-16",
                    "units": -0.0009380874160014231,
                    "gamma": 0.0009711048845371756,
                    "vega": 1013.3814838594814,
                    "tau": 0.2328767123287671,
                    "delta_t_1": -0.17396422697933,
                    "option_price_t_1": 8.38,
                    "underlying_t_1": 5572.85,
                    "Option_PnL": 0.001923079202802918,
                    "Delta_PnL": 0.0006739897834360525,
                    "Total_PnL": 0.0012490894193668656,
                    "delta_t": -0.16022755190497429,
                    "option_price_t": 6.33,
                    "underlying_price_t": 5576.98
                }
            },
            "sv_2024-05-24_2024-08-16": {
                "call": {
                    "start_date": "2024-05-24",
                    "strike": 5250,
                    "maturity": "2024-08-16",
                    "units": -0.0009539268359963632,
                    "gamma": 0.0010016221346045853,
                    "vega": 999.4110637393858,
                    "tau": 0.23013698630136986,
                    "delta_t_1": 0.8679831799766395,
                    "option_price_t_1": 327.55,
                    "underlying_t_1": 5572.85,
                    "Option_PnL": -0.002651916604069864,
                    "Delta_PnL": -0.0034196088126065612,
                    "Total_PnL": 0.0007676922085366974,
                    "delta_t": 0.8810287217913357,
                    "option_price_t": 330.33,
                    "underlying_price_t": 5576.98
                },
                "put": {
                    "start_date": "2024-05-24",
                    "strike": 5250,
                    "maturity": "2024-08-16",
                    "units": -0.0009539268359963632,
                    "gamma": 0.0010016221346045853,
                    "vega": 999.4110637393858,
                    "tau": 0.23013698630136986,
                    "delta_t_1": -0.13201682002336046,
                    "option_price_t_1": 4.7,
                    "underlying_t_1": 5572.85,
                    "Option_PnL": 0.0012878012285950904,
                    "Delta_PnL": 0.0005201090200576557,
                    "Total_PnL": 0.0007676922085374348,
                    "delta_t": -0.11897127820866427,
                    "option_price_t": 3.35,
                    "underlying_price_t": 5576.98
                }
            },
            "sv_2024-05-28_2024-08-16": {
                "call": {
                    "start_date": "2024-05-28",
                    "strike": 5300,
                    "maturity": "2024-08-16",
                    "units": -0.0009697772362045647,
                    "gamma": 0.0010910683373282265,
                    "vega": 989.7265560170744,
                    "tau": 0.2191780821917808,
                    "delta_t_1": 0.8329358029913734,
                    "option_price_t_1": 281.23,
                    "underlying_t_1": 5572.85,
                    "Option_PnL": -0.0020171366513054793,
                    "Delta_PnL": -0.003336057807367473,
                    "Total_PnL": 0.0013189211560619939,
                    "delta_t": 0.8467286491031147,
                    "option_price_t": 283.31,
                    "underlying_price_t": 5576.98
                },
                "put": {
                    "start_date": "2024-05-28",
                    "strike": 5300,
                    "maturity": "2024-08-16",
                    "units": -0.0009697772362045647,
                    "gamma": 0.0010910683373282265,
                    "vega": 989.7265560170744,
                    "tau": 0.2191780821917808,
                    "delta_t_1": -0.16706419700862662,
                    "option_price_t_1": 8.38,
                    "underlying_t_1": 5572.85,
                    "Option_PnL": 0.0019880433342193585,
                    "Delta_PnL": 0.0006691221781566025,
                    "Total_PnL": 0.0013189211560627558,
                    "delta_t": -0.15327135089688526,
                    "option_price_t": 6.33,
                    "underlying_price_t": 5576.98
                }
            },
            "sv_2024-05-29_2024-08-16": {
                "call": {
                    "start_date": "2024-05-29",
                    "strike": 5300,
                    "maturity": "2024-08-16",
                    "units": -0.0009839034783431448,
                    "gamma": 0.0010862286632017774,
                    "vega": 976.0651435701056,
                    "tau": 0.21643835616438356,
                    "delta_t_1": 0.8343725096172045,
                    "option_price_t_1": 281.23,
                    "underlying_t_1": 5572.85,
                    "Option_PnL": -0.0020465192349537254,
                    "Delta_PnL": -0.003390490519662424,
                    "Total_PnL": 0.0013439712847086987,
                    "delta_t": 0.8481739714201383,
                    "option_price_t": 283.31,
                    "underlying_price_t": 5576.98
                },
                "put": {
                    "start_date": "2024-05-29",
                    "strike": 5300,
                    "maturity": "2024-08-16",
                    "units": -0.0009839034783431448,
                    "gamma": 0.0010862286632017774,
                    "vega": 976.0651435701056,
                    "tau": 0.21643835616438356,
                    "delta_t_1": -0.16562749038279545,
                    "option_price_t_1": 8.38,
                    "underlying_t_1": 5572.85,
                    "Option_PnL": 0.0020170021306034473,
                    "Delta_PnL": 0.0006730308458939766,
                    "Total_PnL": 0.0013439712847094706,
                    "delta_t": -0.15182602857986172,
                    "option_price_t": 6.33,
                    "underlying_price_t": 5576.98
                }
            },
            "sv_2024-05-30_2024-08-16": {
                "call": {
                    "start_date": "2024-05-30",
                    "strike": 5250,
                    "maturity": "2024-08-16",
                    "units": -0.0009961443388313096,
                    "gamma": 0.001100561063379877,
                    "vega": 965.5197166728339,
                    "tau": 0.2136986301369863,
                    "delta_t_1": 0.8763720252337734,
                    "option_price_t_1": 327.55,
                    "underlying_t_1": 5572.85,
                    "Option_PnL": -0.0027692812619510136,
                    "Delta_PnL": -0.0036054612207003915,
                    "Total_PnL": 0.0008361799587493779,
                    "delta_t": 0.8892886520475134,
                    "option_price_t": 330.33,
                    "underlying_price_t": 5576.98
                },
                "put": {
                    "start_date": "2024-05-30",
                    "strike": 5250,
                    "maturity": "2024-08-16",
                    "units": -0.0009961443388313096,
                    "gamma": 0.001100561063379877,
                    "vega": 965.5197166728339,
                    "tau": 0.2136986301369863,
                    "delta_t_1": -0.12362797476622656,
                    "option_price_t_1": 4.7,
                    "underlying_t_1": 5572.85,
                    "Option_PnL": 0.001344794857422268,
                    "Delta_PnL": 0.0005086148986721201,
                    "Total_PnL": 0.0008361799587501479,
                    "delta_t": -0.1107113479524866,
                    "option_price_t": 3.35,
                    "underlying_price_t": 5576.98
                }
            },
            "sv_2024-05-31_2024-08-16": {
                "call": {
                    "start_date": "2024-05-31",
                    "strike": 5250,
                    "maturity": "2024-08-16",
                    "units": -0.0009989371818967987,
                    "gamma": 0.0010844626160474336,
                    "vega": 961.1850182594872,
                    "tau": 0.21095890410958903,
                    "delta_t_1": 0.8778262135670397,
                    "option_price_t_1": 327.55,
                    "underlying_t_1": 5572.85,
                    "Option_PnL": -0.002777045365673073,
                    "Delta_PnL": -0.003621569097619336,
                    "Total_PnL": 0.000844523731946263,
                    "delta_t": 0.890715589300494,
                    "option_price_t": 330.33,
                    "underlying_price_t": 5576.98
                },
                "put": {
                    "start_date": "2024-05-31",
                    "strike": 5250,
                    "maturity": "2024-08-16",
                    "units": -0.0009989371818967987,
                    "gamma": 0.0010844626160474336,
                    "vega": 961.1850182594872,
                    "tau": 0.21095890410958903,
                    "delta_t_1": -0.12217378643296029,
                    "option_price_t_1": 4.7,
                    "underlying_t_1": 5572.85,
                    "Option_PnL": 0.0013485651955606782,
                    "Delta_PnL": 0.0005040414636136435,
                    "Total_PnL": 0.0008445237319470348,
                    "delta_t": -0.10928441069950601,
                    "option_price_t": 3.35,
                    "underlying_price_t": 5576.98
                }
            },
            "sv_2024-06-03_2024-08-16": {
                "call": {
                    "start_date": "2024-06-03",
                    "strike": 5300,
                    "maturity": "2024-08-16",
                    "units": -0.0010168767053958835,
                    "gamma": 0.0011461435037897194,
                    "vega": 948.9561827179683,
                    "tau": 0.20273972602739726,
                    "delta_t_1": 0.8418619513100359,
                    "option_price_t_1": 281.23,
                    "underlying_t_1": 5572.85,
                    "Option_PnL": -0.0021151035472234216,
                    "Delta_PnL": -0.0035355683047525294,
                    "Total_PnL": 0.0014204647575291078,
                    "delta_t": 0.8556905268926884,
                    "option_price_t": 283.31,
                    "underlying_price_t": 5576.98
                },
                "put": {
                    "start_date": "2024-06-03",
                    "strike": 5300,
                    "maturity": "2024-08-16",
                    "units": -0.0010168767053958835,
                    "gamma": 0.0011461435037897194,
                    "vega": 948.9561827179683,
                    "tau": 0.20273972602739726,
                    "delta_t_1": -0.15813804868996406,
                    "option_price_t_1": 8.38,
                    "underlying_t_1": 5572.85,
                    "Option_PnL": 0.002084597246061562,
                    "Delta_PnL": 0.0006641324885316551,
                    "Total_PnL": 0.0014204647575299066,
                    "delta_t": -0.14430947310731157,
                    "option_price_t": 6.33,
                    "underlying_price_t": 5576.98
                }
            },
            "sv_2024-06-04_2024-08-16": {
                "call": {
                    "start_date": "2024-06-04",
                    "strike": 5300,
                    "maturity": "2024-08-16",
                    "units": -0.001023670913634419,
                    "gamma": 0.0011672883306025337,
                    "vega": 944.017762402959,
                    "tau": 0.2,
                    "delta_t_1": 0.8434240960686383,
                    "option_price_t_1": 281.23,
                    "underlying_t_1": 5572.85,
                    "Option_PnL": -0.002129235500359575,
                    "Delta_PnL": -0.0035657953929652793,
                    "Total_PnL": 0.0014365598926057042,
                    "delta_t": 0.8572544721382667,
                    "option_price_t": 283.31,
                    "underlying_price_t": 5576.98
                },
                "put": {
                    "start_date": "2024-06-04",
                    "strike": 5300,
                    "maturity": "2024-08-16",
                    "units": -0.001023670913634419,
                    "gamma": 0.0011672883306025337,
                    "vega": 944.017762402959,
                    "tau": 0.2,
                    "delta_t_1": -0.15657590393136167,
                    "option_price_t_1": 8.38,
                    "underlying_t_1": 5572.85,
                    "Option_PnL": 0.0020985253729505597,
                    "Delta_PnL": 0.0006619654803440515,
                    "Total_PnL": 0.0014365598926065083,
                    "delta_t": -0.14274552786173333,
                    "option_price_t": 6.33,
                    "underlying_price_t": 5576.98
                }
            },
            "sv_2024-06-05_2024-08-16": {
                "call": {
                    "start_date": "2024-06-05",
                    "strike": 5300,
                    "maturity": "2024-08-16",
                    "units": -0.0010321679750208814,
                    "gamma": 0.0011415548194725507,
                    "vega": 931.6410246621404,
                    "tau": 0.19726027397260273,
                    "delta_t_1": 0.845008736875746,
                    "option_price_t_1": 281.23,
                    "underlying_t_1": 5572.85,
                    "Option_PnL": -0.0021469093880434166,
                    "Delta_PnL": -0.0036021486516493472,
                    "Total_PnL": 0.0014552392636059306,
                    "delta_t": 0.8588395463391666,
                    "option_price_t": 283.31,
                    "underlying_price_t": 5576.98
                },
                "put": {
                    "start_date": "2024-06-05",
                    "strike": 5300,
                    "maturity": "2024-08-16",
                    "units": -0.0010321679750208814,
                    "gamma": 0.0011415548194725507,
                    "vega": 931.6410246621404,
                    "tau": 0.19726027397260273,
                    "delta_t_1": -0.15499126312425404,
                    "option_price_t_1": 8.38,
                    "underlying_t_1": 5572.85,
                    "Option_PnL": 0.0021159443487928074,
                    "Delta_PnL": 0.0006607050851860673,
                    "Total_PnL": 0.00145523926360674,
                    "delta_t": -0.1411604536608334,
                    "option_price_t": 6.33,
                    "underlying_price_t": 5576.98
                }
            },
            "sv_2024-06-06_2024-08-16": {
                "call": {
                    "start_date": "2024-06-06",
                    "strike": 5350,
                    "maturity": "2024-08-16",
                    "units": -0.0010228164609873223,
                    "gamma": 0.00116933765623319,
                    "vega": 941.0878343332445,
                    "tau": 0.19452054794520549,
                    "delta_t_1": 0.7983017386284703,
                    "option_price_t_1": 237.02,
                    "underlying_t_1": 5572.85,
                    "Option_PnL": -0.0012273797531847752,
                    "Delta_PnL": -0.0033722117370988593,
                    "Total_PnL": 0.002144831983914084,
                    "delta_t": 0.8125305950473887,
                    "option_price_t": 238.22,
                    "underlying_price_t": 5576.98
                },
                "put": {
                    "start_date": "2024-06-06",
                    "strike": 5350,
                    "maturity": "2024-08-16",
                    "units": -0.0010228164609873223,
                    "gamma": 0.00116933765623319,
                    "vega": 941.0878343332445,
                    "tau": 0.19452054794520549,
                    "delta_t_1": -0.20169826137152969,
                    "option_price_t_1": 14.17,
                    "underlying_t_1": 5572.85,
                    "Option_PnL": 0.002996852230692854,
                    "Delta_PnL": 0.0008520202467779626,
                    "Total_PnL": 0.0021448319839148912,
                    "delta_t": -0.18746940495261133,
                    "option_price_t": 11.24,
                    "underlying_price_t": 5576.98
                }
            },
            "sv_2024-06-07_2024-08-16": {
                "call": {
                    "start_date": "2024-06-07",
                    "strike": 5350,
                    "maturity": "2024-08-16",
                    "units": -0.0010326424574975302,
                    "gamma": 0.001190945965539966,
                    "vega": 933.9287402157321,
                    "tau": 0.1917808219178082,
                    "delta_t_1": 0.799871020827907,
                    "option_price_t_1": 237.02,
                    "underlying_t_1": 5572.85,
                    "Option_PnL": -0.0012391709489970244,
                    "Delta_PnL": -0.0034113006074762337,
                    "Total_PnL": 0.0021721296584792096,
                    "delta_t": 0.8141340449285339,
                    "option_price_t": 238.22,
                    "underlying_price_t": 5576.98
                },
                "put": {
                    "start_date": "2024-06-07",
                    "strike": 5350,
                    "maturity": "2024-08-16",
                    "units": -0.0010326424574975302,
                    "gamma": 0.001190945965539966,
                    "vega": 933.9287402157321,
                    "tau": 0.1917808219178082,
                    "delta_t_1": -0.20012897917209305,
                    "option_price_t_1": 14.17,
                    "underlying_t_1": 5572.85,
                    "Option_PnL": 0.003025642400467763,
                    "Delta_PnL": 0.00085351274198774,
                    "Total_PnL": 0.002172129658480023,
                    "delta_t": -0.18586595507146608,
                    "option_price_t": 11.24,
                    "underlying_price_t": 5576.98
                }
            },
            "sv_2024-06-10_2024-08-16": {
                "call": {
                    "start_date": "2024-06-10",
                    "strike": 5350,
                    "maturity": "2024-08-16",
                    "units": -0.001057291515791933,
                    "gamma": 0.0012377377764807881,
                    "vega": 914.4333138245379,
                    "tau": 0.18356164383561643,
                    "delta_t_1": 0.804744533348168,
                    "option_price_t_1": 237.02,
                    "underlying_t_1": 5572.85,
                    "Option_PnL": -0.0012687498189503075,
                    "Delta_PnL": -0.0035140087137287084,
                    "Total_PnL": 0.0022452588947784007,
                    "delta_t": 0.81910665157764,
                    "option_price_t": 238.22,
                    "underlying_price_t": 5576.98
                },
                "put": {
                    "start_date": "2024-06-10",
                    "strike": 5350,
                    "maturity": "2024-08-16",
                    "units": -0.001057291515791933,
                    "gamma": 0.0012377377764807881,
                    "vega": 914.4333138245379,
                    "tau": 0.18356164383561643,
                    "delta_t_1": -0.19525546665183202,
                    "option_price_t_1": 14.17,
                    "underlying_t_1": 5572.85,
                    "Option_PnL": 0.003097864141270363,
                    "Delta_PnL": 0.0008526052464911285,
                    "Total_PnL": 0.0022452588947792346,
                    "delta_t": -0.18089334842236005,
                    "option_price_t": 11.24,
                    "underlying_price_t": 5576.98
                }
            },
            "sv_2024-06-11_2024-08-16": {
                "call": {
                    "start_date": "2024-06-11",
                    "strike": 5350,
                    "maturity": "2024-08-16",
                    "units": -0.0010658473397880104,
                    "gamma": 0.0012392940360200246,
                    "vega": 906.4760512290732,
                    "tau": 0.18082191780821918,
                    "delta_t_1": 0.8064268417233196,
                    "option_price_t_1": 237.02,
                    "underlying_t_1": 5572.85,
                    "Option_PnL": -0.0012790168077456004,
                    "Delta_PnL": -0.0035498502434550784,
                    "Total_PnL": 0.002270833435709478,
                    "delta_t": 0.8208206646932347,
                    "option_price_t": 238.22,
                    "underlying_price_t": 5576.98
                },
                "put": {
                    "start_date": "2024-06-11",
                    "strike": 5350,
                    "maturity": "2024-08-16",
                    "units": -0.0010658473397880104,
                    "gamma": 0.0012392940360200246,
                    "vega": 906.4760512290732,
                    "tau": 0.18082191780821918,
                    "delta_t_1": -0.19357315827668042,
                    "option_price_t_1": 14.17,
                    "underlying_t_1": 5572.85,
                    "Option_PnL": 0.00312293270557887,
                    "Delta_PnL": 0.0008520992698685514,
                    "Total_PnL": 0.002270833435710319,
                    "delta_t": -0.17917933530676533,
                    "option_price_t": 11.24,
                    "underlying_price_t": 5576.98
                }
            },
            "sv_2024-06-12_2024-08-16": {
                "call": {
                    "start_date": "2024-06-12",
                    "strike": 5400,
                    "maturity": "2024-08-16",
                    "units": -0.0010633688898186735,
                    "gamma": 0.001366289070640044,
                    "vega": 908.1553376922251,
                    "tau": 0.1780821917808219,
                    "delta_t_1": 0.7511138982414803,
                    "option_price_t_1": 195.6,
                    "underlying_t_1": 5572.85,
                    "Option_PnL": -0.0002445748446583142,
                    "Delta_PnL": -0.0032986770581740913,
                    "Total_PnL": 0.003054102213515777,
                    "delta_t": 0.7652238165858999,
                    "option_price_t": 195.83,
                    "underlying_price_t": 5576.98
                },
                "put": {
                    "start_date": "2024-06-12",
                    "strike": 5400,
                    "maturity": "2024-08-16",
                    "units": -0.0010633688898186735,
                    "gamma": 0.001366289070640044,
                    "vega": 908.1553376922251,
                    "tau": 0.1780821917808219,
                    "delta_t_1": -0.24888610175851966,
                    "option_price_t_1": 22.75,
                    "underlying_t_1": 5572.85,
                    "Option_PnL": 0.0041471386702928255,
                    "Delta_PnL": 0.001093036456776179,
                    "Total_PnL": 0.0030541022135166466,
                    "delta_t": -0.23477618341410011,
                    "option_price_t": 18.85,
                    "underlying_price_t": 5576.98
                }
            },
            "sv_2024-06-13_2024-08-16": {
                "call": {
                    "start_date": "2024-06-13",
                    "strike": 5400,
                    "maturity": "2024-08-16",
                    "units": -0.0010748829798965112,
                    "gamma": 0.0013858192562345758,
                    "vega": 898.2255628833155,
                    "tau": 0.17534246575342466,
                    "delta_t_1": 0.7526656166139577,
                    "option_price_t_1": 195.6,
                    "underlying_t_1": 5572.85,
                    "Option_PnL": -0.00024722308537621714,
                    "Delta_PnL": -0.003341283413316691,
                    "Total_PnL": 0.0030940603279404743,
                    "delta_t": 0.7668396947081186,
                    "option_price_t": 195.83,
                    "underlying_price_t": 5576.98
                },
                "put": {
                    "start_date": "2024-06-13",
                    "strike": 5400,
                    "maturity": "2024-08-16",
                    "units": -0.0010748829798965112,
                    "gamma": 0.0013858192562345758,
                    "vega": 898.2255628833155,
                    "tau": 0.17534246575342466,
                    "delta_t_1": -0.2473343833860423,
                    "option_price_t_1": 22.75,
                    "underlying_t_1": 5572.85,
                    "Option_PnL": 0.004192043621596393,
                    "Delta_PnL": 0.0010979832936550396,
                    "Total_PnL": 0.003094060327941353,
                    "delta_t": -0.23316030529188136,
                    "option_price_t": 18.85,
                    "underlying_price_t": 5576.98
                }
            },
            "sv_2024-06-14_2024-08-16": {
                "call": {
                    "start_date": "2024-06-14",
                    "strike": 5450,
                    "maturity": "2024-08-16",
                    "units": -0.001074685920672687,
                    "gamma": 0.0014316694232676134,
                    "vega": 899.5147056371721,
                    "tau": 0.1726027397260274,
                    "delta_t_1": 0.6892161463805323,
                    "option_price_t_1": 157.7,
                    "underlying_t_1": 5572.85,
                    "Option_PnL": 0.0008167612997112324,
                    "Delta_PnL": -0.0030590533708071905,
                    "Total_PnL": 0.003875814670518423,
                    "delta_t": 0.702156839322544,
                    "option_price_t": 156.94,
                    "underlying_price_t": 5576.98
                },
                "put": {
                    "start_date": "2024-06-14",
                    "strike": 5450,
                    "maturity": "2024-08-16",
                    "units": -0.001074685920672687,
                    "gamma": 0.0014316694232676134,
                    "vega": 899.5147056371721,
                    "tau": 0.1726027397260274,
                    "delta_t_1": -0.3107838536194677,
                    "option_price_t_1": 34.85,
                    "underlying_t_1": 5572.85,
                    "Option_PnL": 0.00525521415208944,
                    "Delta_PnL": 0.0013793994815701474,
                    "Total_PnL": 0.003875814670519293,
                    "delta_t": -0.297843160677456,
                    "option_price_t": 29.96,
                    "underlying_price_t": 5576.98
                }
            },
            "sv_2024-06-17_2024-08-16": {
                "call": {
                    "start_date": "2024-06-17",
                    "strike": 5450,
                    "maturity": "2024-08-16",
                    "units": -0.0010961953990305574,
                    "gamma": 0.0014968926097035666,
                    "vega": 879.740397451954,
                    "tau": 0.1643835616438356,
                    "delta_t_1": 0.6931020868505731,
                    "option_price_t_1": 157.7,
                    "underlying_t_1": 5572.85,
                    "Option_PnL": 0.0008331085032632137,
                    "Delta_PnL": -0.0031378720660820256,
                    "Total_PnL": 0.003970980569345239,
                    "delta_t": 0.7063012527958457,
                    "option_price_t": 156.94,
                    "underlying_price_t": 5576.98
                },
                "put": {
                    "start_date": "2024-06-17",
                    "strike": 5450,
                    "maturity": "2024-08-16",
                    "units": -0.0010961953990305574,
                    "gamma": 0.0014968926097035666,
                    "vega": 879.740397451954,
                    "tau": 0.1643835616438356,
                    "delta_t_1": -0.30689791314942694,
                    "option_price_t_1": 34.85,
                    "underlying_t_1": 5572.85,
                    "Option_PnL": 0.005360395501259427,
                    "Delta_PnL": 0.001389414931913299,
                    "Total_PnL": 0.003970980569346128,
                    "delta_t": -0.29369874720415434,
                    "option_price_t": 29.96,
                    "underlying_price_t": 5576.98
                }
            },
            "sv_2024-06-18_2024-08-16": {
                "call": {
                    "start_date": "2024-06-18",
                    "strike": 5450,
                    "maturity": "2024-08-16",
                    "units": -0.0011116884140846134,
                    "gamma": 0.0015426785020449343,
                    "vega": 867.6147317196388,
                    "tau": 0.16164383561643836,
                    "delta_t_1": 0.6944599915648907,
                    "option_price_t_1": 157.7,
                    "underlying_t_1": 5572.85,
                    "Option_PnL": 0.000844883194704296,
                    "Delta_PnL": -0.0031884555131381693,
                    "Total_PnL": 0.004033338707842465,
                    "delta_t": 0.7077482696421724,
                    "option_price_t": 156.94,
                    "underlying_price_t": 5576.98
                },
                "put": {
                    "start_date": "2024-06-18",
                    "strike": 5450,
                    "maturity": "2024-08-16",
                    "units": -0.0011116884140846134,
                    "gamma": 0.0015426785020449343,
                    "vega": 867.6147317196388,
                    "tau": 0.16164383561643836,
                    "delta_t_1": -0.3055400084351093,
                    "option_price_t_1": 34.85,
                    "underlying_t_1": 5572.85,
                    "Option_PnL": 0.00543615634487376,
                    "Delta_PnL": 0.0014028176370303937,
                    "Total_PnL": 0.004033338707843366,
                    "delta_t": -0.2922517303578276,
                    "option_price_t": 29.96,
                    "underlying_price_t": 5576.98
                }
            },
            "sv_2024-06-20_2024-08-16": {
                "call": {
                    "start_date": "2024-06-20",
                    "strike": 5500,
                    "maturity": "2024-08-16",
                    "units": -0.0011232823767122063,
                    "gamma": 0.0015758846778548918,
                    "vega": 859.8893469709011,
                    "tau": 0.15616438356164383,
                    "delta_t_1": 0.6233102796050394,
                    "option_price_t_1": 123.93,
                    "underlying_t_1": 5572.85,
                    "Option_PnL": 0.0018534159215751469,
                    "Delta_PnL": -0.0028916337580145402,
                    "Total_PnL": 0.004745049679589687,
                    "delta_t": 0.6345128620232872,
                    "option_price_t": 122.28,
                    "underlying_price_t": 5576.98
                },
                "put": {
                    "start_date": "2024-06-20",
                    "strike": 5500,
                    "maturity": "2024-08-16",
                    "units": -0.0011232823767122063,
                    "gamma": 0.0015758846778548918,
                    "vega": 859.8893469709011,
                    "tau": 0.15616438356164383,
                    "delta_t_1": -0.3766897203949606,
                    "option_price_t_1": 51.08,
                    "underlying_t_1": 5572.85,
                    "Option_PnL": 0.006492572137396554,
                    "Delta_PnL": 0.0017475224578059724,
                    "Total_PnL": 0.004745049679590581,
                    "delta_t": -0.36548713797671284,
                    "option_price_t": 45.3,
                    "underlying_price_t": 5576.98
                }
            },
            "sv_2024-06-21_2024-08-16": {
                "call": {
                    "start_date": "2024-06-21",
                    "strike": 5450,
                    "maturity": "2024-08-16",
                    "units": -0.0011341058645571757,
                    "gamma": 0.001586509295081452,
                    "vega": 851.1004194338244,
                    "tau": 0.15342465753424658,
                    "delta_t_1": 0.6987393397054442,
                    "option_price_t_1": 157.7,
                    "underlying_t_1": 5572.85,
                    "Option_PnL": 0.0008619204570634433,
                    "Delta_PnL": -0.0032727953016107557,
                    "Total_PnL": 0.004134715758674199,
                    "delta_t": 0.7123043458713887,
                    "option_price_t": 156.94,
                    "underlying_price_t": 5576.98
                },
                "put": {
                    "start_date": "2024-06-21",
                    "strike": 5450,
                    "maturity": "2024-08-16",
                    "units": -0.0011341058645571757,
                    "gamma": 0.001586509295081452,
                    "vega": 851.1004194338244,
                    "tau": 0.15342465753424658,
                    "delta_t_1": -0.3012606602945558,
                    "option_price_t_1": 34.85,
                    "underlying_t_1": 5572.85,
                    "Option_PnL": 0.00554577767768459,
                    "Delta_PnL": 0.0014110619190094728,
                    "Total_PnL": 0.004134715758675117,
                    "delta_t": -0.2876956541286113,
                    "option_price_t": 29.96,
                    "underlying_price_t": 5576.98
                }
            },
            "sv_2024-06-24_2024-09-20": {
                "call": {
                    "start_date": "2024-06-24",
                    "strike": 5450,
                    "maturity": "2024-09-20",
                    "units": -0.0009060908937665973,
                    "gamma": 0.001267500529780448,
                    "vega": 1066.9044557148866,
                    "tau": 0.2410958904109589,
                    "delta_t_1": 0.6648115214969434,
                    "option_price_t_1": 184.91,
                    "underlying_t_1": 5572.85,
                    "Option_PnL": 0.0021202526914138407,
                    "Delta_PnL": -0.0024878280193384402,
                    "Total_PnL": 0.0046080807107522805,
                    "delta_t": 0.6760107136438228,
                    "option_price_t": 182.57,
                    "underlying_price_t": 5576.98
                },
                "put": {
                    "start_date": "2024-06-24",
                    "strike": 5450,
                    "maturity": "2024-09-20",
                    "units": -0.0009060908937665973,
                    "gamma": 0.001267500529780448,
                    "vega": 1066.9044557148866,
                    "tau": 0.2410958904109589,
                    "delta_t_1": -0.33518847850305655,
                    "option_price_t_1": 62.06,
                    "underlying_t_1": 5572.85,
                    "Option_PnL": 0.0058624080826698835,
                    "Delta_PnL": 0.0012543273719168816,
                    "Total_PnL": 0.004608080710753002,
                    "delta_t": -0.3239892863561772,
                    "option_price_t": 55.59,
                    "underlying_price_t": 5576.98
                }
            },
            "sv_2024-06-25_2024-09-20": {
                "call": {
                    "start_date": "2024-06-25",
                    "strike": 5450,
                    "maturity": "2024-09-20",
                    "units": -0.0009105328602469557,
                    "gamma": 0.0012614150603660497,
                    "vega": 1060.9359916845654,
                    "tau": 0.23835616438356164,
                    "delta_t_1": 0.665583248700153,
                    "option_price_t_1": 184.91,
                    "underlying_t_1": 5572.85,
                    "Option_PnL": 0.0021306468929778795,
                    "Delta_PnL": -0.0025029262811774432,
                    "Total_PnL": 0.004633573174155322,
                    "delta_t": 0.6768407037425153,
                    "option_price_t": 182.57,
                    "underlying_price_t": 5576.98
                },
                "put": {
                    "start_date": "2024-06-25",
                    "strike": 5450,
                    "maturity": "2024-09-20",
                    "units": -0.0009105328602469557,
                    "gamma": 0.0012614150603660497,
                    "vega": 1060.9359916845654,
                    "tau": 0.23835616438356164,
                    "delta_t_1": -0.33441675129984705,
                    "option_price_t_1": 62.06,
                    "underlying_t_1": 5572.85,
                    "Option_PnL": 0.005891147605797803,
                    "Delta_PnL": 0.0012575744316417556,
                    "Total_PnL": 0.004633573174156047,
                    "delta_t": -0.32315929625748474,
                    "option_price_t": 55.59,
                    "underlying_price_t": 5576.98
                }
            },
            "sv_2024-06-26_2024-09-20": {
                "call": {
                    "start_date": "2024-06-26",
                    "strike": 5450,
                    "maturity": "2024-09-20",
                    "units": -0.0009171048666083986,
                    "gamma": 0.0012650465946218636,
                    "vega": 1053.4367907941298,
                    "tau": 0.2356164383561644,
                    "delta_t_1": 0.6663683555044162,
                    "option_price_t_1": 184.91,
                    "underlying_t_1": 5572.85,
                    "Option_PnL": 0.002146025387863656,
                    "Delta_PnL": -0.002523965503179555,
                    "Total_PnL": 0.00466999089104321,
                    "delta_t": 0.6776848629053265,
                    "option_price_t": 182.57,
                    "underlying_price_t": 5576.98
                },
                "put": {
                    "start_date": "2024-06-26",
                    "strike": 5450,
                    "maturity": "2024-09-20",
                    "units": -0.0009171048666083986,
                    "gamma": 0.0012650465946218636,
                    "vega": 1053.4367907941298,
                    "tau": 0.2356164383561644,
                    "delta_t_1": -0.3336316444955838,
                    "option_price_t_1": 62.06,
                    "underlying_t_1": 5572.85,
                    "Option_PnL": 0.005933668486956338,
                    "Delta_PnL": 0.0012636775959123975,
                    "Total_PnL": 0.004669990891043941,
                    "delta_t": -0.3223151370946735,
                    "option_price_t": 55.59,
                    "underlying_price_t": 5576.98
                }
            },
            "sv_2024-06-27_2024-09-20": {
                "call": {
                    "start_date": "2024-06-27",
                    "strike": 5500,
                    "maturity": "2024-09-20",
                    "units": -0.0009159466350228504,
                    "gamma": 0.0012861167569831536,
                    "vega": 1055.1741435099905,
                    "tau": 0.2328767123287671,
                    "delta_t_1": 0.6050193491247747,
                    "option_price_t_1": 153.66,
                    "underlying_t_1": 5572.85,
                    "Option_PnL": 0.002738680438718331,
                    "Delta_PnL": -0.0022887032546218588,
                    "Total_PnL": 0.00502738369334019,
                    "delta_t": 0.6141818454764355,
                    "option_price_t": 150.67,
                    "underlying_price_t": 5576.98
                },
                "put": {
                    "start_date": "2024-06-27",
                    "strike": 5500,
                    "maturity": "2024-09-20",
                    "units": -0.0009159466350228504,
                    "gamma": 0.0012861167569831536,
                    "vega": 1055.1741435099905,
                    "tau": 0.2328767123287671,
                    "delta_t_1": -0.39498065087522527,
                    "option_price_t_1": 80.81,
                    "underlying_t_1": 5572.85,
                    "Option_PnL": 0.006521540041362699,
                    "Delta_PnL": 0.0014941563480217806,
                    "Total_PnL": 0.005027383693340918,
                    "delta_t": -0.3858181545235645,
                    "option_price_t": 73.69,
                    "underlying_price_t": 5576.98
                }
            },
            "sv_2024-06-28_2024-09-20": {
                "call": {
                    "start_date": "2024-06-28",
                    "strike": 5500,
                    "maturity": "2024-09-20",
                    "units": -0.0009327228321895682,
                    "gamma": 0.0013461560399296727,
                    "vega": 1039.1166899018547,
                    "tau": 0.23013698630136986,
                    "delta_t_1": 0.605502394523427,
                    "option_price_t_1": 153.66,
                    "underlying_t_1": 5572.85,
                    "Option_PnL": 0.0027888412682468174,
                    "Delta_PnL": -0.0023324832013506417,
                    "Total_PnL": 0.005121324469597459,
                    "delta_t": 0.6147213589526506,
                    "option_price_t": 150.67,
                    "underlying_price_t": 5576.98
                },
                "put": {
                    "start_date": "2024-06-28",
                    "strike": 5500,
                    "maturity": "2024-09-20",
                    "units": -0.0009327228321895682,
                    "gamma": 0.0013461560399296727,
                    "vega": 1039.1166899018547,
                    "tau": 0.23013698630136986,
                    "delta_t_1": -0.394497605476573,
                    "option_price_t_1": 80.81,
                    "underlying_t_1": 5572.85,
                    "Option_PnL": 0.00664098656518973,
                    "Delta_PnL": 0.0015196620955915281,
                    "Total_PnL": 0.0051213244695982015,
                    "delta_t": -0.38527864104734943,
                    "option_price_t": 73.69,
                    "underlying_price_t": 5576.98
                }
            },
            "sv_2024-07-01_2024-09-20": {
                "call": {
                    "start_date": "2024-07-01",
                    "strike": 5450,
                    "maturity": "2024-09-20",
                    "units": -0.0009486083508034125,
                    "gamma": 0.001371261506140681,
                    "vega": 1022.3633203275834,
                    "tau": 0.2219178082191781,
                    "delta_t_1": 0.6705082174777446,
                    "option_price_t_1": 184.91,
                    "underlying_t_1": 5572.85,
                    "Option_PnL": 0.0022197435408799885,
                    "Delta_PnL": -0.002626885237795908,
                    "Total_PnL": 0.004846628778675897,
                    "delta_t": 0.6821324641313276,
                    "option_price_t": 182.57,
                    "underlying_price_t": 5576.98
                },
                "put": {
                    "start_date": "2024-07-01",
                    "strike": 5450,
                    "maturity": "2024-09-20",
                    "units": -0.0009486083508034125,
                    "gamma": 0.001371261506140681,
                    "vega": 1022.3633203275834,
                    "tau": 0.2219178082191781,
                    "delta_t_1": -0.3294917825222554,
                    "option_price_t_1": 62.06,
                    "underlying_t_1": 5572.85,
                    "Option_PnL": 0.006137496029698077,
                    "Delta_PnL": 0.0012908672510214259,
                    "Total_PnL": 0.004846628778676651,
                    "delta_t": -0.31786753586867245,
                    "option_price_t": 55.59,
                    "underlying_price_t": 5576.98
                }
            },
            "sv_2024-07-02_2024-09-20": {
                "call": {
                    "start_date": "2024-07-02",
                    "strike": 5500,
                    "maturity": "2024-09-20",
                    "units": -0.0009421554452081902,
                    "gamma": 0.001359851113535792,
                    "vega": 1027.2294864835596,
                    "tau": 0.2191780821917808,
                    "delta_t_1": 0.6075303553038987,
                    "option_price_t_1": 153.66,
                    "underlying_t_1": 5572.85,
                    "Option_PnL": 0.0028170447811724972,
                    "Delta_PnL": -0.002363962573724129,
                    "Total_PnL": 0.005181007354896626,
                    "delta_t": 0.6169846338722764,
                    "option_price_t": 150.67,
                    "underlying_price_t": 5576.98
                },
                "put": {
                    "start_date": "2024-07-02",
                    "strike": 5500,
                    "maturity": "2024-09-20",
                    "units": -0.0009421554452081902,
                    "gamma": 0.001359851113535792,
                    "vega": 1027.2294864835596,
                    "tau": 0.2191780821917808,
                    "delta_t_1": -0.39246964469610135,
                    "option_price_t_1": 80.81,
                    "underlying_t_1": 5572.85,
                    "Option_PnL": 0.006708146769882318,
                    "Delta_PnL": 0.0015271394149849425,
                    "Total_PnL": 0.005181007354897376,
                    "delta_t": -0.3830153661277236,
                    "option_price_t": 73.69,
                    "underlying_price_t": 5576.98
                }
            },
            "sv_2024-07-03_2024-09-20": {
                "call": {
                    "start_date": "2024-07-03",
                    "strike": 5500,
                    "maturity": "2024-09-20",
                    "units": -0.0009514422337846412,
                    "gamma": 0.0013384202494016902,
                    "vega": 1015.7602614465751,
                    "tau": 0.21643835616438356,
                    "delta_t_1": 0.608062789566199,
                    "option_price_t_1": 153.66,
                    "underlying_t_1": 5572.85,
                    "Option_PnL": 0.002844812279016086,
                    "Delta_PnL": -0.002389356235586479,
                    "Total_PnL": 0.0052341685146025645,
                    "delta_t": 0.617578393686998,
                    "option_price_t": 150.67,
                    "underlying_price_t": 5576.98
                },
                "put": {
                    "start_date": "2024-07-03",
                    "strike": 5500,
                    "maturity": "2024-09-20",
                    "units": -0.0009514422337846412,
                    "gamma": 0.0013384202494016902,
                    "vega": 1015.7602614465751,
                    "tau": 0.21643835616438356,
                    "delta_t_1": -0.39193721043380103,
                    "option_price_t_1": 80.81,
                    "underlying_t_1": 5572.85,
                    "Option_PnL": 0.00677426870454665,
                    "Delta_PnL": 0.0015401001899433273,
                    "Total_PnL": 0.005234168514603323,
                    "delta_t": -0.38242160631300204,
                    "option_price_t": 73.69,
                    "underlying_price_t": 5576.98
                }
            },
            "sv_2024-07-05_2024-09-20": {
                "call": {
                    "start_date": "2024-07-05",
                    "strike": 5550,
                    "maturity": "2024-09-20",
                    "units": -0.0009496811217082097,
                    "gamma": 0.0013491474557739086,
                    "vega": 1016.4359436443823,
                    "tau": 0.21095890410958903,
                    "delta_t_1": 0.541640200869878,
                    "option_price_t_1": 125.84,
                    "underlying_t_1": 5572.85,
                    "Option_PnL": 0.0033143871147616605,
                    "Delta_PnL": -0.002124412005655219,
                    "Total_PnL": 0.005438799120416879,
                    "delta_t": 0.5484731324515779,
                    "option_price_t": 122.35,
                    "underlying_price_t": 5576.98
                },
                "put": {
                    "start_date": "2024-07-05",
                    "strike": 5550,
                    "maturity": "2024-09-20",
                    "units": -0.0009496811217082097,
                    "gamma": 0.0013491474557739086,
                    "vega": 1016.4359436443823,
                    "tau": 0.21095890410958903,
                    "delta_t_1": -0.45835979913012204,
                    "option_price_t_1": 102.99,
                    "underlying_t_1": 5572.85,
                    "Option_PnL": 0.007236570147416548,
                    "Delta_PnL": 0.0017977710269989273,
                    "Total_PnL": 0.0054387991204176206,
                    "delta_t": -0.4515268675484221,
                    "option_price_t": 95.37,
                    "underlying_price_t": 5576.98
                }
            },
            "sv_2024-07-08_2024-09-20": {
                "call": {
                    "start_date": "2024-07-08",
                    "strike": 5550,
                    "maturity": "2024-09-20",
                    "units": -0.0009706850855481817,
                    "gamma": 0.001384686163247757,
                    "vega": 995.4840302316406,
                    "tau": 0.20273972602739726,
                    "delta_t_1": 0.542059329293992,
                    "option_price_t_1": 125.84,
                    "underlying_t_1": 5567.19,
                    "delta_t": 0.5490466184640438,
                    "option_price_t": 122.35,
                    "underlying_price_t": 5576.98,
                    "Option_PnL": 0.003387690948563163,
                    "Delta_PnL": -0.005151193593929402,
                    "Total_PnL": 0.008538884542492565
                },
                "put": {
                    "start_date": "2024-07-08",
                    "strike": 5550,
                    "maturity": "2024-09-20",
                    "units": -0.0009706850855481817,
                    "gamma": 0.001384686163247757,
                    "vega": 995.4840302316406,
                    "tau": 0.20273972602739726,
                    "delta_t_1": -0.45794067070600797,
                    "option_price_t_1": 102.99,
                    "underlying_t_1": 5567.19,
                    "delta_t": -0.4509533815359562,
                    "option_price_t": 95.37,
                    "underlying_price_t": 5576.98,
                    "Option_PnL": 0.0073966203518771355,
                    "Delta_PnL": 0.004351813393587261,
                    "Total_PnL": 0.0030448069582898743
                }
            },
            "sv_2024-07-09_2024-09-20": {
                "call": {
                    "start_date": "2024-07-09",
                    "strike": 5550,
                    "maturity": "2024-09-20",
                    "units": -0.000980158859467834,
                    "delta_t": 0.5492473514354934,
                    "gamma": 0.0014543881200052148,
                    "vega": 987.4115577447877,
                    "tau": 0.2,
                    "option_price_t": 122.35,
                    "underlying_price_t": 5572.85
                },
                "put": {
                    "start_date": "2024-07-09",
                    "strike": 5550,
                    "maturity": "2024-09-20",
                    "units": -0.000980158859467834,
                    "delta_t": -0.4507526485645066,
                    "gamma": 0.0014543881200052148,
                    "vega": 987.4115577447877,
                    "tau": 0.2,
                    "option_price_t": 95.37,
                    "underlying_price_t": 5572.85
                }
            }
        }
    }
}